{
  "versions": [
    {
      "reading": [
        { "11":"<span class='lem'>Kristes</span> ] <span class='rdg'>christes <a>D</a> </span>" },
        { "18":"<span class='lem'>Kristes</span> ] <span class='rdg'>christes <a>D</a> </span>" },
        { "19":"<span class='lem'>betent</span> ] <span class='rdg'>betten <a>D</a></span>" },
        { "22":"<span class='lem'>durch</span> ] <span class='rdg'><span class='note'>om.</span> <a>Fr33</a></span>" },
        { "23":"<span class='lem'>der zem urteillîchem</span> ] <span class='rdg'>dem zer vrteilichen <a>Fr33</a></span>" },
        { "28":"<span class='lem'>an</span> ] <span class='rdg'><span class='note'>om.</span> <a>Fr33</a></span>" },
        { "29":"<span class='lem'>In</span> ] <span class='rdg'>÷n <a>D</a></span>" },
        { "30":"<span class='lem'>ein</span> ] <span class='rdg'><span class='note'>om.</span> <a>Fr33</a></span>" },
        { "30":"<span class='lem'>ergraben</span> ] <span class='rdg'>ergraben <span class='note'>nachträglich korrigiert zu:</span> gegraben <a>D</a></span>" }
      ],
      "handle": "*D",
      "distribution": "<ul><li><a data-thirties=\"107\">D</a></li><li><a data-thirties=\"107\">Fr33</a> <span>(107.19-30)</span></li></ul>",
      "structure": [
        { "19":"<span class='note'>Initiale</span> <a>Fr33</a>" },
        { "29":"<span class='note'>Initiale</span> <a>D</a>" }
      ]
    },
    {
      "reading": [
        { "04":"<span class='lem'>dâ inne</span> ] <span class='rdg'>Danne <a>m</a></span>" },
        { "06":"<span class='lem'>vor</span> ] <span class='rdg'>Von <a>n</a> Won <a>o</a></span>" },
        { "07":"<span class='lem'>rubîn</span> ] <span class='rdg'>rúbin <a>n</a> <a>o</a></span>" },
        { "07":"<span class='lem'>der</span> ] <span class='rdg'>ein <a>n</a></span>" },
        { "10":"<span class='lem'>meister</span> ] <span class='rdg'>martel <a>n</a> (<a>o</a>)</span>" },
        { "11":"<span class='lem'>Kristus</span> ] <span class='rdg'>cristus <a>m</a> <a>n</a> cristu̽s <a>o</a></span>" },
        { "11":"<span class='lem'>erlôste</span> ] <span class='rdg'>erlúst <a>o</a></span>" },
        { "12":"<span class='lem'>liez</span> ] <span class='rdg'>Liesse <a>n</a></span>" },
        { "12":"<span class='lem'>ze trôste</span> ] <span class='rdg'>[zestoste]: zestroste <a>m</a></span>" },
        { "13":"<span class='lem'>sêle</span> ] <span class='rdg'>selen <a>o</a></span>" },
        { "13":"<span class='lem'>über</span> ] <span class='rdg'>v́be <a>n</a></span>" },
        { "14":"<span class='lem'>die koste</span> ] <span class='rdg'>den kosten <a>n</a> <a>o</a></span>" },
        { "16":"<span class='lem'>der</span> ] <span class='rdg'>den <a>n</a> des <a>o</a></span>" },
        { "17":"<span class='lem'>iht</span> ] <span class='rdg'>nicht <a>n</a> (<a>o</a>)</span>" },
        { "18":"<span class='lem'>Kristus</span> ] <span class='rdg'>cristus <a>m</a> <a>n</a> cristu̽s <a>o</a></span>" },
        { "19":"<span class='lem'>betent</span> ] <span class='rdg'>bieten <a>o</a></span>" },
        { "20":"<span class='lem'>als ir</span> ] <span class='rdg'>also an iren <a>n</a> vnd an jrem <a>o</a></span>" },
        { "22":"<span class='lem'>toufes lêre</span> ] <span class='rdg'>touffes ere vnd lere <a>m</a></span>" },
        { "23":"<span class='lem'>urteillîchem</span> ] <span class='rdg'>vrteilichen <a>n</a> (<a>o</a>)</span>" },
        { "24":"<span class='lem'>lœsen</span> ] <span class='rdg'>lassen <a>m</a></span>" },
        { "27":"<span class='lem'>bîhte</span> ] <span class='rdg'>gebiht <a>o</a></span>" },
        { "29":"<span class='lem'>in</span> ] <span class='rdg'>An <a>o</a></span>" },
        { "29":"<span class='lem'>den</span> ] <span class='rdg'>ein <a>n</a></span>" },
        { "29":"<span class='lem'>adamas</span> ] <span class='rdg'>adamast <a>m</a></span>" },
        { "30":"<span class='lem'>epitafjum</span> ] <span class='rdg'>appitaffium <a>m</a> appitasum <a>n</a> apitagsum <a>o</a></span>" }
      ],
      "handle": "*m",
      "distribution": "<ul><li><a data-thirties=\"107\">m</a></li><li><a data-thirties=\"107\">n</a></li><li><a data-thirties=\"107\">o</a></li></ul>",
      "structure": [  ]
    },
    {
      "reading": [
        { "01":"<span class='lem'>wart</span> ] <span class='rdg'>er wart <a>Q</a></span>" },
        { "01":"<span class='lem'>sîn grap</span> ] <span class='rdg'>si sarc <a>I</a> er <a>O</a> <span class='note'>om.</span> <a>L</a> <a>M</a> <a>Q</a> <a>R</a> <a>Z</a> <a>Fr21</a></span>" },
        { "01":"<span class='lem'>gehêrt</span> ] <span class='rdg'>ge erit <a>M</a></span>" },
        { "04":"<span class='lem'>dâr</span> ] <span class='rdg'>Do er <a>Q</a> (<a>R</a>)</span>" },
        { "05":"<span class='lem'>sîn junger</span> ] <span class='rdg'>der iunge <a>I</a> (<a>Fr21</a>)</span>" },
        { "06":"<span class='rdg'>Von iamer wart vil levten we <a>O</a> (<a>M</a> <a>R</a> <a>Fr21</a>) Von iamer wart vil luͦte we <a>L</a> Vor iamer wart (ovch <a>Z</a>) vil leuten wee <a>Q</a> (<a>Z</a>)</span>" },
        { "06":"<span class='lem'>Sarrazinen</span> ] <span class='rdg'>sarazinen <a>G</a> den sarrazinen <a>I</a></span>" },
        { "07":"<span class='lem'>rubîn</span> ] <span class='rdg'>rubein <a>Q</a></span>" },
        { "08":"<span class='lem'>obe</span> ] <span class='rdg'>Vff <a>M</a></span>" },
        { "09":"<span class='lem'>hie</span> ] <span class='rdg'>da <a>L</a></span>" },
        { "11":"<span class='lem'>als</span> ] <span class='rdg'>al <a>I</a></span>" },
        { "11":"<span class='lem'>Krist</span> ] <span class='rdg'>christ <a>G</a> crist <a>I</a> <a>M</a> christes <a>O</a> <a>Fr21</a> cristus <a>L</a> <a>R</a> cristes <a>Q</a> <a>Z</a></span>" },
        { "11":"<span class='lem'>des tôdes</span> ] <span class='rdg'><span class='note'>om.</span> <a>I</a> tot <a>O</a> (<a>L</a>) <a>Q</a> <a>Z</a> <a>Fr21</a> von dem tod <a>R</a></span>" },
        { "11":"<span class='lem'>erlôste</span> ] <span class='rdg'>loste <a>G</a> erlost <a>R</a> <a>Fr21</a></span>" },
        { "13":"<span class='lem'>ze scherme der sêle</span> ] <span class='rdg'>der sel zesherme <a>I</a> Zcu beschermene der sele <a>M</a> Ze schirme der selbe <a>R</a></span>" },
        { "14":"<span class='lem'>bâruc</span> ] <span class='rdg'>brauc <a>Q</a></span>" },
        { "15":"<span class='lem'>was</span> ] <span class='rdg'>wart <a>L</a></span>" },
        { "15":"<span class='lem'>smarât</span> ] <span class='rdg'>smarade <a>I</a> smarac <a>Q</a> schmarat <a>R</a></span>" },
        { "17":"<span class='lem'>niht</span> ] <span class='rdg'><span class='note'>om.</span> <a>Z</a></span>" },
        { "18":"<span class='lem'>Kristes</span> ] <span class='rdg'>christes <a>G</a> <a>O</a> cristes <a>I</a> (<a>L</a>) <a>M</a> <a>Q</a> <a>Z</a> <a>Fr21</a> cristus <a>R</a></span>" },
        { "18":"<span class='lem'>tôt</span> ] <span class='rdg'>tuͤt <a>I</a></span>" },
        { "18":"<span class='lem'>uns</span> ] <span class='rdg'>vnd <a>R</a></span>" },
        { "20":"<span class='lem'>an in</span> ] <span class='rdg'>an an <a>I</a> Jn an <a>O</a></span>" },
        { "20":"<span class='lem'>an ir</span> ] <span class='rdg'>ir <a>O</a></span>" },
        { "21":"<span class='lem'>des</span> ] <span class='rdg'><span class='note'>om.</span> <a>R</a></span>" },
        { "22":"<span class='lem'>des</span> ] <span class='rdg'><span class='note'>om.</span> <a>L</a> <a>R</a></span>" },
        { "22":"<span class='lem'>toufes</span> ] <span class='rdg'>taufel <a>I</a> toifers <a>M</a> tewfels <a>Q</a></span>" },
        { "23":"<span class='lem'>urteillîchen</span> ] <span class='rdg'>vrtailichem <a>I</a> (<a>O</a> <a>L</a> <a>Q</a> <a>Z</a>) ordentlicheme <a>M</a></span>" },
        { "23":"<span class='lem'>ende</span> ] <span class='rdg'>tage ende <a>L</a></span>" },
        { "24":"<span class='lem'>uns</span> ] <span class='rdg'>Vsz <a>L</a></span>" },
        { "24":"<span class='lem'>der</span> ] <span class='rdg'><span class='note'>om.</span> <a>I</a> <a>Z</a></span>" },
        { "24":"<span class='lem'>gebende</span> ] <span class='rdg'>[ende]: bende <a>M</a></span>" },
        { "25":"<span class='lem'>manlîche triwe</span> ] <span class='rdg'>mancliche truwe <a>M</a> trewlich manheit <a>Z</a></span>" },
        { "26":"<span class='lem'>gît</span> ] <span class='rdg'>Get <a>M</a></span>" },
        { "26":"<span class='lem'>ime</span> ] <span class='rdg'>in <a>I</a> vns <a>O</a> <span class='note'>om.</span> <a>M</a></span>" },
        { "26":"<span class='lem'>ze</span> ] <span class='rdg'>zcu ome <a>M</a></span>" },
        { "26":"<span class='lem'>liehten</span> ] <span class='rdg'>lichten <a>L</a> (<a>M</a> <a>Q</a>)</span>" },
        { "27":"<span class='lem'>riwic</span> ] <span class='rdg'>Rúwe <a>R</a> rewe <a>Z</a></span>" },
        { "28":"<span class='lem'>der</span> ] <span class='rdg'>Kein <a>Q</a></span>" },
        { "28":"<span class='lem'>an</span> ] <span class='rdg'><span class='note'>om.</span> <a>Z</a></span>" },
        { "28":"<span class='lem'>sîhte</span> ] <span class='rdg'>lihte <a>O</a> nichte <a>Q</a></span>" },
        { "29":"<span class='lem'>in</span> ] <span class='rdg'>an <a>I</a> (<a>L</a> <a>R</a>)</span>" },
        { "29":"<span class='lem'>sînen</span> ] <span class='rdg'>sinem <a>I</a> <a>O</a> <a>L</a> <a>R</a> <a>Z</a></span>" },
        { "29":"<span class='lem'>den</span> ] <span class='rdg'>der <a>I</a> (<a>O</a>) dem <a>Q</a> <a>R</a> <span class='note'>om.</span> <a>Z</a></span>" },
        { "30":"<span class='lem'>epitafjum</span> ] <span class='rdg'>ein epitafium <a>I</a> (<a>L</a> <a>Q</a> <a>R</a>) [Einen]: Ein epitafivum <a>Z</a></span>" },
        { "30":"<span class='lem'>ergraben</span> ] <span class='rdg'>er grab <a>M</a></span>" }
      ],
      "handle": "*G",
      "distribution": "<ul><li><a data-thirties=\"107\">G</a></li><li><a data-thirties=\"107\">I</a></li><li><a data-thirties=\"107\">O</a></li><li><a data-thirties=\"107\">L</a></li><li><a data-thirties=\"107\">M</a></li><li><a data-thirties=\"107\">Q</a></li><li><a data-thirties=\"107\">R</a></li><li><a data-thirties=\"107\">Z</a></li><li><a data-thirties=\"107\">Fr21</a> <span>(107.1-20)</span></li></ul>",
      "structure": [
        { "17":"<span class='note'>Initiale</span> <a>I</a>" },
        { "29":"<span class='note'>Initiale</span> <a>L</a> <a>Q</a> <a>R</a> <a>Z</a>" }
      ]
    },
    {
      "reading": [
        { "01":"<span class='lem'>gehêret</span> ] <span class='rdg'>gekeret <a>U</a> er geheret <a>W</a></span>" },
        { "06":"<span class='lem'>vor</span> ] <span class='rdg'>von <a>V</a> (<a>W</a>)</span>" },
        { "07":"<span class='lem'>der</span> ] <span class='rdg'>sein <a>W</a></span>" },
        { "08":"<span class='lem'>sîme</span> ] <span class='rdg'>e sinem <a>T</a></span>" },
        { "11":"<span class='rdg'>da mit vns criste erlôste <a>T</a></span>" },
        { "11":"<span class='lem'>Kristes</span> ] <span class='rdg'>cristus <a>U</a> cristes <a>V</a> christus <a>W</a></span>" },
        { "11":"<span class='lem'>jost</span> ] <span class='rdg'>dot <a>V</a> (<a>W</a>)</span>" },
        { "12":"<span class='lem'>hiez</span> ] <span class='rdg'>lie <a>T</a></span>" },
        { "13":"<span class='lem'>sêle</span> ] <span class='rdg'>selen <a>V</a> <a>W</a></span>" },
        { "14":"<span class='lem'>kost</span> ] <span class='rdg'>selben koste <a>W</a></span>" },
        { "15":"<span class='lem'>daz</span> ] <span class='rdg'>ez <a>T</a></span>" },
        { "15":"<span class='lem'>smarât</span> ] <span class='rdg'>marat <a>U</a></span>" },
        { "18":"<span class='lem'>Kristes</span> ] <span class='rdg'>cristus <a>U</a> cristes <a>V</a> <a>T</a> christus <a>W</a></span>" },
        { "18":"<span class='lem'>uns lie den</span> ] <span class='rdg'>[*]: vns liden <a>U</a> hie lie den <a>V</a> lies vns den <a>W</a></span>" },
        { "19":"<span class='lem'>betent</span> ] <span class='rdg'>betten <a>V</a></span>" },
        { "20":"<span class='lem'>in</span> ] <span class='rdg'>ir <a>U</a> in reht <a>T</a></span>" },
        { "20":"<span class='lem'>ir</span> ] <span class='rdg'>in <a>U</a> ein <a>W</a></span>" },
        { "21":"<span class='lem'>durch</span> ] <span class='rdg'><span class='note'>om.</span> <a>W</a></span>" },
        { "21":"<span class='lem'>kriuzes</span> ] <span class='rdg'><span class='note'>om.</span> <a>T</a></span>" },
        { "23":"<span class='lem'>sô er</span> ] <span class='rdg'>Doch er <a>W</a> der <a>T</a></span>" },
        { "23":"<span class='lem'>urteillîchem</span> ] <span class='rdg'>vrteillichen <a>V</a> vrtailischem <a>W</a></span>" },
        { "24":"<span class='lem'>wolte von gebende</span> ] <span class='rdg'>[*]: sol der gebende <a>V</a> solt von gebende <a>W</a> sol der bende <a>T</a></span>" },
        { "25":"<span class='lem'>manlîche</span> ] <span class='rdg'>man lichte <a>U</a> manlichen <a>T</a></span>" },
        { "26":"<span class='lem'>im</span> ] <span class='rdg'><span class='note'>om.</span> <a>W</a></span>" },
        { "26":"<span class='lem'>liehten</span> ] <span class='rdg'>lichten <a>U</a></span>" },
        { "27":"<span class='rdg'>Vnd seiner treúwen pflichte <a>W</a></span>" },
        { "27":"<span class='lem'>und</span> ] <span class='rdg'>vnde ouch <a>T</a></span>" },
        { "28":"<span class='lem'>valsch</span> ] <span class='rdg'>valsche <a>U</a></span>" },
        { "28":"<span class='lem'>im sîhte</span> ] <span class='rdg'>an [*]: imme sihte <a>V</a> im nichte <a>W</a> an im sihte <a>T</a></span>" },
        { "29":"<span class='lem'>sînen</span> ] <span class='rdg'>seinem <a>W</a> (<a>T</a>)</span>" },
        { "29":"<span class='lem'>dem</span> ] <span class='rdg'>[*]: den <a>V</a> den <a>W</a></span>" }
      ],
      "handle": "*T",
      "distribution": "<ul><li><a data-thirties=\"107\">U</a></li><li><a data-thirties=\"107\">V</a></li><li><a data-thirties=\"107\">W</a></li><li><a data-thirties=\"107\">T</a></li></ul>",
      "structure": [
        { "09":"<span class='note'>Versal</span> <a>T</a>" },
        { "29":"<span class='note'>Initiale</span> <a>U</a> <a>V</a> <a>W</a> <a>T</a>" }
      ]
    }
  ],
  "meta": {
    "generated-by": "parzival-static-api/src/generate.xsl",
    "task": "metadata-syn-apps",
    "generated-on": "2026-02-02T20:32:21.639161207+01:00",
    "description": "Apparatus information (distribution, structural, readings)."
  }
}