{
  "versions": [
    {
      "reading": [
        { "22":"<span class='lem'>die</span> ] <span class='rdg'>[div]: die <a>D</a></span>" },
        { "25":"<span class='lem'>morgens</span> ] <span class='rdg'>morgen <a>D</a></span>" }
      ],
      "handle": "*D",
      "distribution": "<ul><li><a data-thirties=\"202\">D</a></li></ul>",
      "structure": [
        { "03":"<span class='note'>Majuskel</span> <a>D</a>" },
        { "19":"<span class='note'>Majuskel</span> <a>D</a>" },
        { "29":"<span class='note'>Initiale</span> <a>D</a>" }
      ]
    },
    {
      "reading": [
        { "02":"<span class='lem'>ie</span> ] <span class='rdg'>E <a>n</a></span>" },
        { "04":"<span class='lem'>vriundinne</span> ] <span class='rdg'>frunden <a>o</a></span>" },
        { "04":"<span class='lem'>schouwen</span> ] <span class='rdg'>scho̽nen <a>n</a> schonen <a>o</a> (<a>Fr69</a>)</span>" },
        { "05":"<span class='lem'>denket</span> ] <span class='rdg'>dancket <a>n</a> <a>o</a></span>" },
        { "06":"<span class='lem'>mîniu</span> ] <span class='rdg'>nún <a>n</a></span>" },
        { "09":"<span class='lem'>erboten</span> ] <span class='rdg'>Gebotten <a>o</a></span>" },
        { "10":"<span class='lem'>hete</span> ] <span class='rdg'>hertte <a>m</a> hat <a>n</a> <span class='note'>om.</span> <a>o</a></span>" },
        { "10":"<span class='lem'>mich</span> ] <span class='rdg'>[mit]: mich <a>o</a></span>" },
        { "11":"<span class='lem'>grôzen</span> ] <span class='rdg'>blossen <a>n</a> <a>o</a></span>" },
        { "12":"<span class='lem'>müese</span> ] <span class='rdg'>Musse <a>m</a></span>" },
        { "13":"<span class='lem'>gîtes</span> ] <span class='rdg'>gu̽tes <a>n</a> gattez <a>o</a></span>" },
        { "16":"<span class='lem'>beider</span> ] <span class='rdg'>beide <a>m</a></span>" },
        { "19":"<span class='lem'>Waleise</span> ] <span class='rdg'>wageleise <a>o</a> </span>" },
        { "20":"<span class='lem'>kranc</span> ] <span class='rdg'>Drang <a>m</a> Trang <a>n</a> <a>o</a></span>" },
        { "21":"<span class='lem'>der rôte</span> ] <span class='rdg'>den roten <a>n</a> <a>o</a> (<a>Fr69</a>)</span>" },
        { "22":"<span class='lem'>die</span> ] <span class='rdg'>Der die <a>m</a> <a>n</a> <a>o</a></span>" },
        { "22":"<span class='lem'>er</span> ] <span class='rdg'><span class='note'>om.</span> <a>n</a> <a>o</a></span>" },
        { "25":"<span class='lem'>bant</span> ] <span class='rdg'>ban <a>o</a></span>" },
        { "27":"<span class='lem'>brût</span> ] <span class='rdg'>brúgt <a>o</a></span>" },
        { "28":"<span class='lem'>ir</span> ] <span class='rdg'>irs <a>m</a> (<a>n</a>) <a>o</a></span>" },
        { "30":"<span class='lem'>vrô</span> ] <span class='rdg'><span class='note'>om.</span> <a>m</a> by <a>n</a> (<a>o</a>)</span>" }
      ],
      "handle": "*m",
      "distribution": "<ul><li><a data-thirties=\"202\">m</a></li><li><a data-thirties=\"202\">n</a></li><li><a data-thirties=\"202\">o</a></li><li><a data-thirties=\"202\">Fr69</a> <span>(202.3-6, 20-23 und 27-30)</span></li></ul>",
      "structure": [  ]
    },
    {
      "reading": [
        { "01":"<span class='lem'>vüeget</span> ] <span class='rdg'>Fvͦgent <a>O</a> (<a>M</a> <a>Q</a> <a>Z</a>) Fu̽gte <a>L</a> Fvͦgten <a>Fr21</a></span>" },
        { "01":"<span class='lem'>mit ir</span> ] <span class='rdg'>mir <a>G</a> mir iz <a>M</a></span>" },
        { "02":"<span class='lem'>des</span> ] <span class='rdg'>der <a>I</a> (<a>L</a>)</span>" },
        { "02":"<span class='lem'>ie sich</span> ] <span class='rdg'>er si <a>I</a> sich îe <a>O</a> (<a>Q</a> <a>R</a> <a>Fr21</a>) er ie sich <a>L</a> ie <a>M</a></span>" },
        { "02":"<span class='lem'>bewarte</span> ] <span class='rdg'>bewart <a>I</a> gewarte <a>Q</a></span>" },
        { "04":"<span class='lem'>wol</span> ] <span class='rdg'>der wol <a>I</a></span>" },
        { "04":"<span class='lem'>schônen</span> ] <span class='rdg'>schowen <a>L</a></span>" },
        { "05":"<span class='lem'>er denket</span> ] <span class='rdg'>Erdencken <a>Q</a> Er gedenket <a>R</a> <a>Fr21</a></span>" },
        { "05":"<span class='lem'>als ez lîht</span> ] <span class='rdg'>liht als ez <a>I</a> (<a>L</a>) licht daz <a>R</a></span>" },
        { "06":"<span class='lem'>gedienet</span> ] <span class='rdg'>gedien <a>Z</a></span>" },
        { "06":"<span class='lem'>mîniu</span> ] <span class='rdg'>manigiv <a>O</a> menig <a>R</a></span>" },
        { "07":"<span class='lem'>wîbe</span> ] <span class='rdg'>libe <a>R</a></span>" },
        { "08":"<span class='lem'>hât</span> ] <span class='rdg'>hat nach lon <a>R</a></span>" },
        { "09":"<span class='lem'>lige ich</span> ] <span class='rdg'>lige <a>I</a> lege ich <a>M</a></span>" },
        { "10":"<span class='lem'>genüeget</span> ] <span class='rdg'>benvget <a>L</a> (<a>Z</a>) nenúget <a>Q</a> gerowen <a>R</a></span>" },
        { "11":"<span class='lem'>ich</span> ] <span class='rdg'>ich mich <a>O</a></span>" },
        { "11":"<span class='lem'>mîner blôzen</span> ] <span class='rdg'>plosser <a>Q</a></span>" },
        { "12":"<span class='lem'>solte</span> ] <span class='rdg'>So so <a>O</a></span>" },
        { "12":"<span class='lem'>rüeren</span> ] <span class='rdg'>bru̽rren <a>R</a></span>" },
        { "13":"<span class='lem'>nû</span> ] <span class='rdg'><span class='note'>om.</span> <a>O</a></span>" },
        { "13":"<span class='lem'>ihtes</span> ] <span class='rdg'>guͤtes <a>I</a> (<a>L</a>) gites <a>O</a> <a>Q</a> (<a>R</a>) <a>Z</a> <a>Fr21</a> <span class='note'>om.</span> <a>M</a></span>" },
        { "14":"<span class='lem'>untriwe</span> ] <span class='rdg'>Vntriwes <a>Fr21</a></span>" },
        { "14":"<span class='lem'>es vür</span> ] <span class='rdg'>fvr <a>O</a> fvͦre <a>Fr21</a></span>" },
        { "15":"<span class='lem'>si</span> ] <span class='rdg'>sin <a>R</a></span>" },
        { "16":"<span class='lem'>beider</span> ] <span class='rdg'>zweier <a>I</a></span>" },
        { "16":"<span class='lem'>breiten</span> ] <span class='rdg'>bereiten <a>M</a></span>" },
        { "17":"<span class='lem'>süeziu</span> ] <span class='rdg'>suzen <a>I</a> (<a>Fr21</a>) su̽sze <a>R</a></span>" },
        { "18":"<span class='lem'>sint</span> ] <span class='rdg'>Sit <a>M</a></span>" },
        { "18":"<span class='lem'>sitebære</span> ] <span class='rdg'>niht vnmere <a>O</a> (<a>Fr21</a>) gebere <a>L</a> <a>M</a> sitegebere <a>Q</a> (<a>R</a>) <a>Z</a></span>" },
        { "19":"<span class='lem'>Sus</span> ] <span class='rdg'>Es <a>Q</a></span>" },
        { "19":"<span class='lem'>Waleise</span> ] <span class='rdg'>walæise <a>O</a> vollaise <a>R</a></span>" },
        { "20":"<span class='lem'>vreise</span> ] <span class='rdg'>reise <a>R</a> <a>Z</a></span>" },
        { "21":"<span class='lem'>rôten</span> ] <span class='rdg'>roter <a>M</a></span>" },
        { "22":"<span class='lem'>er</span> ] <span class='rdg'>ir <a>M</a></span>" },
        { "23":"<span class='lem'>wânde</span> ] <span class='rdg'>wanden <a>I</a></span>" },
        { "23":"<span class='lem'>iedoch</span> ] <span class='rdg'>doch <a>O</a> <a>R</a> <a>Z</a> <a>Fr21</a></span>" },
        { "24":"<span class='lem'>minniclîchen</span> ] <span class='rdg'>mundiglichen <a>Q</a></span>" },
        { "25":"<span class='lem'>morgens</span> ] <span class='rdg'>morgens do <a>R</a></span>" },
        { "25":"<span class='lem'>ir</span> ] <span class='rdg'>er <a>M</a></span>" },
        { "25":"<span class='lem'>houbet</span> ] <span class='rdg'>har uff <a>R</a></span>" },
        { "26":"<span class='lem'>dô</span> ] <span class='rdg'>Sie <a>L</a> (<a>R</a>) Da <a>M</a></span>" },
        { "26":"<span class='lem'>gap</span> ] <span class='rdg'>gag <a>R</a></span>" },
        { "27":"<span class='lem'>magetbære</span> ] <span class='rdg'>mageberev <a>I</a> (<a>O</a> <a>R</a> <a>Z</a> <a>Fr21</a>)</span>" },
        { "28":"<span class='lem'>ir</span> ] <span class='rdg'>irs <a>Z</a></span>" },
        { "29":"<span class='lem'>si</span> ] <span class='rdg'>÷i <a>O</a></span>" }
      ],
      "handle": "*G",
      "distribution": "<ul><li><a data-thirties=\"202\">G</a></li><li><a data-thirties=\"202\">I</a></li><li><a data-thirties=\"202\">O</a></li><li><a data-thirties=\"202\">L</a></li><li><a data-thirties=\"202\">M</a></li><li><a data-thirties=\"202\">Q</a></li><li><a data-thirties=\"202\">R</a></li><li><a data-thirties=\"202\">Z</a></li><li><a data-thirties=\"202\">Fr21</a></li></ul>",
      "structure": [
        { "05":"<span class='note'>Initiale</span> <a>I</a>" },
        { "09":"<span class='note'>Initiale</span> <a>R</a>" },
        { "13":"<span class='note'>Initiale</span> <a>Q</a>" },
        { "19":"<span class='note'>Initiale</span> <a>G</a> <a>I</a> <a>Z</a>" },
        { "19":"<span class='note'>Capitulumzeichen</span> <a>L</a>" },
        { "29":"<span class='note'>Initiale</span> <a>O</a> <a>L</a> <a>Fr21</a>" }
      ]
    },
    {
      "reading": [
        { "01":"<span class='lem'>ir</span> ] <span class='rdg'><span class='note'>om.</span> <a>W</a></span>" },
        { "02":"<span class='lem'>der</span> ] <span class='rdg'>[De*]: Dez <a>V</a></span>" },
        { "03":"<span class='lem'>der stæte</span> ] <span class='rdg'>stete <a>V</a> <a>W</a></span>" },
        { "04":"<span class='lem'>vriundinne</span> ] <span class='rdg'>frúndinnen <a>W</a></span>" },
        { "04":"<span class='lem'>schônen</span> ] <span class='rdg'>schowen <a>U</a></span>" },
        { "05":"<span class='lem'>gedenket</span> ] <span class='rdg'>gedenck <a>W</a></span>" },
        { "05":"<span class='lem'>alsez</span> ] <span class='rdg'>[*]: als ez lihte <a>V</a> als es licht <a>W</a></span>" },
        { "06":"<span class='lem'>mîniu jâr</span> ] <span class='rdg'>[m*ar]: mine iar <a>V</a></span>" },
        { "07":"<span class='lem'>lône</span> ] <span class='rdg'>lobe <a>W</a></span>" },
        { "08":"<span class='lem'>diu</span> ] <span class='rdg'>Die hat <a>V</a> <a>W</a></span>" },
        { "09":"<span class='lem'>erbiutet</span> ] <span class='rdg'>[Jrbotten]: V́rbotten <a>V</a> Erbotten <a>W</a></span>" },
        { "09":"<span class='lem'>unde</span> ] <span class='rdg'>nuͦ <a>U</a> (<a>V</a> <a>W</a>)</span>" },
        { "11":"<span class='lem'>blôzen</span> ] <span class='rdg'>blosseu <a>W</a></span>" },
        { "12":"<span class='lem'>müese</span> ] <span class='rdg'>[M*]: Moͤhte <a>V</a></span>" },
        { "13":"<span class='lem'>gîtes</span> ] <span class='rdg'>gutes <a>W</a></span>" },
        { "18":"<span class='lem'>sitebære</span> ] <span class='rdg'>sitte gebêre <a>V</a> (<a>W</a>)</span>" },
        { "19":"<span class='lem'>Waleise</span> ] <span class='rdg'>walleise <a>V</a></span>" },
        { "21":"<span class='lem'>hiez</span> ] <span class='rdg'>lies <a>W</a></span>" },
        { "22":"<span class='lem'>die</span> ] <span class='rdg'>div <a>T</a></span>" },
        { "22":"<span class='lem'>liez</span> ] <span class='rdg'>hies <a>W</a></span>" },
        { "23":"<span class='lem'>ie dô</span> ] <span class='rdg'>ie doch <a>U</a> (<a>V</a>) <a>W</a></span>" },
        { "26":"<span class='lem'>Dô</span> ] <span class='rdg'>Sie <a>U</a></span>" },
        { "26":"<span class='lem'>lant</span> ] <span class='rdg'>auch lant <a>W</a></span>" },
        { "27":"<span class='lem'>dise magtbæriu</span> ] <span class='rdg'>Die maget here <a>W</a></span>" },
        { "28":"<span class='lem'>wand er</span> ] <span class='rdg'>Wan der <a>U</a></span>" },
        { "28":"<span class='lem'>ir</span> ] <span class='rdg'>irs <a>U</a> <a>V</a> (<a>W</a>)</span>" }
      ],
      "handle": "*T",
      "distribution": "<ul><li><a data-thirties=\"202\">T</a></li><li><a data-thirties=\"202\">U</a></li><li><a data-thirties=\"202\">V</a></li><li><a data-thirties=\"202\">W</a></li></ul>",
      "structure": [
        { "19":"<span class='note'>Initiale</span> <a>T</a> <a>U</a> <a>V</a> <a>W</a>" },
        { "26":"<span class='note'>Majuskel</span> <a>T</a>" }
      ]
    }
  ],
  "meta": {
    "generated-by": "parzival-static-api/src/generate.xsl",
    "task": "metadata-syn-apps",
    "generated-on": "2026-02-02T20:32:21.639161207+01:00",
    "description": "Apparatus information (distribution, structural, readings)."
  }
}