{
  "versions": [
    {
      "reading": [
        { "01":"<span class='lem'>Plimizœl</span> ] <span class='rdg'>Plymizoͤl <a>D</a></span>" },
        { "02":"<span class='lem'>Barbigœl</span> ] <span class='rdg'>Parbygoͤl <a>D</a></span>" },
        { "03":"<span class='lem'>Liz</span> ] <span class='rdg'>Lŷz <a>D</a></span>" },
        { "06":"<span class='lem'>Orastegentesin</span> ] <span class='rdg'>Orastegentesîn <a>D</a></span>" },
        { "30":"<span class='lem'>müese</span> ] <span class='rdg'>mvͦse <a>D</a></span>" }
      ],
      "handle": "*D",
      "distribution": "<ul><li><a data-thirties=\"385\">D</a></li></ul>",
      "structure": [ { "23":"<span class='note'>Majuskel</span> <a>D</a>" } ]
    },
    {
      "reading": [
        { "01":"<span class='lem'>erz</span> ] <span class='rdg'>er <a>m</a></span>" },
        { "02":"<span class='lem'>Melianzes</span> ] <span class='rdg'>Melianz <a>m</a> Meliantz <a>n</a> Meliancz <a>o</a></span>" },
        { "02":"<span class='lem'>krîe</span> ] <span class='rdg'>kriegen <a>n</a></span>" },
        { "02":"<span class='lem'>Barbigol</span> ] <span class='rdg'>parbigal <a>m</a> parbigol <a>n</a> <a>o</a></span>" },
        { "03":"<span class='lem'>Liz</span> ] <span class='rdg'>liez <a>m</a> lisz <a>n</a> liesz <a>o</a></span>" },
        { "05":"<span class='lem'>Melianzen</span> ] <span class='rdg'>Meleanczen <a>m</a> meliantzen <a>n</a> meliancz <a>o</a></span>" },
        { "06":"<span class='lem'>Arastegentesin</span> ] <span class='rdg'>arastagente sin <a>m</a> orastegente sin <a>n</a> aregestegente sin <a>o</a></span>" },
        { "07":"<span class='lem'>rœrîne</span> ] <span class='rdg'>ro̽rinen <a>n</a> rorinan <a>o</a></span>" },
        { "09":"<span class='lem'>dâ geschach</span> ] <span class='rdg'>do beschach <a>n</a> <a>o</a></span>" },
        { "10":"<span class='lem'>vlügelingen</span> ] <span class='rdg'>flugenligen <a>o</a></span>" },
        { "14":"<span class='lem'>tâtens</span> ] <span class='rdg'>tattencz <a>m</a> dotens sú <a>n</a></span>" },
        { "16":"<span class='lem'>dâ</span> ] <span class='rdg'>Do <a>n</a> Die <a>o</a></span>" },
        { "16":"<span class='lem'>wæren zwên gebûren</span> ] <span class='rdg'>worent zwen buren <a>o</a></span>" },
        { "18":"<span class='lem'>des anderen</span> ] <span class='rdg'>der ander <a>o</a></span>" },
        { "19":"<span class='rdg'><span class='note'>Verse 385.19-21 kontrahiert zu:</span> Stucket dem helm durch den arm <a>o</a></span>" },
        { "19":"<span class='lem'>stückeht</span> ] <span class='rdg'>Sckuckeht <a>m</a></span>" },
        { "20":"<span class='lem'>Melianz</span> ] <span class='rdg'>Meleancz <a>m</a> Meliantz <a>n</a></span>" },
        { "20":"<span class='lem'>muose</span> ] <span class='rdg'>musse <a>m</a> mu̽ste <a>n</a></span>" },
        { "21":"<span class='lem'>daz steckete</span> ] <span class='rdg'>Das stecket <a>n</a></span>" },
        { "21":"<span class='lem'>helde</span> ] <span class='rdg'>helm <a>n</a></span>" },
        { "22":"<span class='lem'>machte</span> ] <span class='rdg'>machen <a>m</a></span>" },
        { "23":"<span class='lem'>zuckete</span> ] <span class='rdg'>zucke <a>o</a></span>" },
        { "23":"<span class='lem'>Gawan</span> ] <span class='rdg'>gawann <a>o</a></span>" },
        { "24":"<span class='lem'>Brevigariezer</span> ] <span class='rdg'>brevigere ze <a>m</a> brevigarie zu̽ der <a>n</a> brebigarie zer <a>o</a></span>" },
        { "26":"<span class='lem'>der</span> ] <span class='rdg'>Desz <a>o</a></span>" },
        { "27":"<span class='lem'>aber</span> ] <span class='rdg'>aber <a>o</a></span>" },
        { "28":"<span class='lem'>dâ</span> ] <span class='rdg'>Do <a>m</a> <a>n</a> <a>o</a></span>" },
        { "29":"<span class='lem'>undertân</span> ] <span class='rdg'>vnderta <a>o</a></span>" },
        { "30":"<span class='lem'>müese</span> ] <span class='rdg'>mu̽sse <a>m</a> muste <a>o</a></span>" },
        { "30":"<span class='lem'>langer</span> ] <span class='rdg'>langes <a>m</a> <a>n</a> <a>o</a></span>" }
      ],
      "handle": "*m",
      "distribution": "<ul><li><a data-thirties=\"385\">m</a></li><li><a data-thirties=\"385\">n</a></li><li><a data-thirties=\"385\">o</a></li></ul>",
      "structure": [  ]
    },
    {
      "reading": [
        { "01":"<span class='rdg'><span class='note'>Die Verse 370.13-412.12 fehlen</span> <a>Q</a></span>" },
        { "01":"<span class='lem'>erwarp</span> ] <span class='rdg'>erwarf <a>G</a></span>" },
        { "01":"<span class='lem'>zem Blimzol</span> ] <span class='rdg'>zemblimzol <a>G</a> zuͤ dem plimizol <a>I</a> (<a>L</a> <a>Z</a>) ze plimizol <a>O</a> zcu deme blimizol <a>M</a> von pomizol <a>R</a> zem Plẏmizoͤl <a>Fr41</a> </span>" },
        { "02":"<span class='lem'>Melianzes</span> ] <span class='rdg'>Melyanzes <a>O</a> Meliantzes <a>L</a> <a>Z</a> Melianczes <a>R</a> </span>" },
        { "02":"<span class='lem'>Barbigol</span> ] <span class='rdg'>babigol <a>I</a> Parbigoͤl <a>Fr41</a> </span>" },
        { "03":"<span class='lem'>in</span> ] <span class='rdg'>von <a>I</a> <a>L</a> an <a>Fr41</a></span>" },
        { "03":"<span class='lem'>Liz</span> ] <span class='rdg'>Lisz <a>L</a> (<a>M</a>) Lys <a>R</a> Liez <a>Z</a> </span>" },
        { "05":"<span class='lem'>lêrte</span> ] <span class='rdg'>lert <a>I</a></span>" },
        { "05":"<span class='lem'>Melianzen</span> ] <span class='rdg'>Melẏanzen <a>O</a> Meliantzen <a>L</a> (<a>Z</a>) Malianczen <a>R</a> :::eli:::azen <a>Fr41</a> </span>" },
        { "06":"<span class='lem'>Orastegentesin</span> ] <span class='rdg'>orastegente sin <a>G</a> Oraste gentesin <a>O</a> (<a>L</a> <a>M</a>) <a>R</a> (<a>Z</a>) :::gentesin <a>Fr41</a> </span>" },
        { "07":"<span class='lem'>rœrîne</span> ] <span class='rdg'>ror ime <a>G</a></span>" },
        { "07-1":"<span class='lem'>wart dâ</span> ] <span class='rdg'>Do ward <a>R</a></span>" },
        { "07-1":"<span class='lem'>hurte</span> ] <span class='rdg'>hurtes <a>R</a></span>" },
        { "07-2":"<span class='lem'>Gawan</span> ] <span class='rdg'>:::n <a>Fr41</a> </span>" },
        { "08":"<span class='lem'>in den</span> ] <span class='rdg'>in dē <a>L</a> (<a>M</a>) im <a>R</a> (<a>Z</a> <a>Fr41</a>)</span>" },
        { "09":"<span class='lem'>rîchiu</span> ] <span class='rdg'>riche <a>R</a></span>" },
        { "09":"<span class='lem'>al</span> ] <span class='rdg'><span class='note'>om.</span> <a>I</a> <a>R</a></span>" },
        { "10":"" },
        { "10":"<span class='lem'>vlügelingen</span> ] <span class='rdg'>:::enliche <a>Fr41</a></span>" },
        { "11":"<span class='rdg'>ein wenc hinder sinen satelbogen <a>I</a></span>" },
        { "11":"<span class='lem'>unde</span> ] <span class='rdg'>Vnden <a>L</a></span>" },
        { "11":"<span class='lem'>hinderen</span> ] <span class='rdg'><span class='note'>om.</span> <a>R</a></span>" },
        { "12":"<span class='lem'>helde</span> ] <span class='rdg'>heldin <a>M</a></span>" },
        { "12":"<span class='lem'>vür</span> ] <span class='rdg'><span class='note'>om.</span> <a>I</a> <a>R</a> fvͦren <a>O</a></span>" },
        { "12":"<span class='lem'>unbetrogen</span> ] <span class='rdg'>en betrogen <a>M</a></span>" },
        { "13":"<span class='lem'>hinder den orsen</span> ] <span class='rdg'>Hinderm rosze <a>L</a></span>" },
        { "14":"<span class='lem'>dô</span> ] <span class='rdg'>Da <a>O</a> <a>L</a> <a>M</a> <a>Z</a></span>" },
        { "14":"<span class='lem'>kunden</span> ] <span class='rdg'>da chunden <a>I</a></span>" },
        { "15":"<span class='lem'>tûren</span> ] <span class='rdg'>durnen <a>R</a></span>" },
        { "16":"<span class='lem'>wære</span> ] <span class='rdg'>wærn <a>O</a> (<a>Z</a>)</span>" },
        { "17":"<span class='lem'>gedroschen</span> ] <span class='rdg'>Zedroschen <a>O</a> Getrosche <a>R</a></span>" },
        { "18":"<span class='lem'>ietweder</span> ] <span class='rdg'>ir ietdweder <a>I</a></span>" },
        { "18":"<span class='lem'>andern</span> ] <span class='rdg'>ander <a>L</a> (<a>R</a>)</span>" },
        { "18":"<span class='lem'>garbe</span> ] <span class='rdg'>grabe <a>M</a> <a>R</a></span>" },
        { "20":"<span class='lem'>Melianz</span> ] <span class='rdg'>Melyanz <a>O</a> Meliantz <a>L</a> <a>Z</a> Meliancz <a>R</a> </span>" },
        { "20":"<span class='lem'>muose</span> ] <span class='rdg'>ouch muste <a>Z</a></span>" },
        { "21":"<span class='lem'>stach</span> ] <span class='rdg'>stachte <a>O</a> (<a>L</a> <a>R</a>) stecke <a>Z</a></span>" },
        { "21":"<span class='lem'>den helt</span> ] <span class='rdg'>dem helde <a>O</a> <a>L</a> (<a>M</a>) <a>Z</a> dem helden <a>R</a></span>" },
        { "21":"<span class='lem'>arm</span> ] <span class='rdg'>armen <a>I</a></span>" },
        { "22":"<span class='lem'>bluotic</span> ] <span class='rdg'>Blutet <a>M</a></span>" },
        { "22":"<span class='lem'>im</span> ] <span class='rdg'>in <a>O</a> <a>L</a> <a>Z</a></span>" },
        { "23":"<span class='lem'>dô</span> ] <span class='rdg'>Da <a>M</a> <a>Z</a></span>" },
        { "23":"<span class='lem'>zuct</span> ] <span class='rdg'>zcucte <a>M</a> (<a>R</a> <a>Z</a>)</span>" },
        { "23":"<span class='lem'>hêr</span> ] <span class='rdg'>er <a>M</a></span>" },
        { "24":"<span class='lem'>in Brevegariezære</span> ] <span class='rdg'>in preregariezare <a>G</a> inparbirazare <a>I</a> Jn prevegariezzerte <a>O</a> Jn Brevegarsszare <a>L</a> Jn prefegariezer <a>M</a> Jn Breuegariezere <a>R</a> Jn brevigariezzere <a>Z</a> </span>" },
        { "25":"<span class='lem'>twanc</span> ] <span class='rdg'>twant <a>Z</a></span>" },
        { "25":"<span class='lem'>umbe</span> ] <span class='rdg'><span class='note'>om.</span> <a>O</a> <a>L</a> <a>M</a> <a>R</a> <a>Z</a></span>" },
        { "26":"<span class='lem'>dô</span> ] <span class='rdg'>vil <a>I</a> <a>L</a> <span class='note'>om.</span> <a>O</a> <a>M</a> <a>R</a> <a>Z</a></span>" },
        { "28":"<span class='lem'>dâne</span> ] <span class='rdg'>Denne <a>R</a></span>" },
        { "28":"<span class='lem'>sô gâhes</span> ] <span class='rdg'>so hahes <a>G</a> sin fachen <a>R</a></span>" },
        { "29":"<span class='lem'>würde</span> ] <span class='rdg'>werre <a>R</a></span>" },
        { "30":"<span class='lem'>müese in</span> ] <span class='rdg'>moͮse in <a>G</a> (<a>M</a>) muͦst in da <a>I</a> mvͦses in <a>O</a> (<a>Z</a>) mu̽ste insz <a>L</a> mu̽st in sin <a>R</a></span>" },
        { "30":"<span class='lem'>lenger hân erlân</span> ] <span class='rdg'>lenger ledic lan <a>I</a> lenger han verlon <a>R</a></span>" }
      ],
      "handle": "*G",
      "distribution": "<ul><li><a data-thirties=\"385\">G</a></li><li><a data-thirties=\"385\">I</a></li><li><a data-thirties=\"385\">O</a></li><li><a data-thirties=\"385\">L</a></li><li><a data-thirties=\"385\">M</a></li><li><a data-thirties=\"385\">Q</a></li><li><a data-thirties=\"385\">R</a></li><li><a data-thirties=\"385\">Z</a></li><li><a data-thirties=\"385\">Fr41</a> <span>(385.1-7, 7¹-7² und 8-16)</span></li></ul>",
      "structure": [
        { "07":"<span class='note'>Initiale</span> <a>G</a>" },
        { "07-2":"<span class='note'>Initiale</span> <a>I</a>" }
      ]
    },
    {
      "reading": [
        { "01":"<span class='lem'>ê</span> ] <span class='rdg'><span class='note'>om.</span> <a>V</a> <a>W</a></span>" },
        { "01":"<span class='lem'>si</span> ] <span class='rdg'>[*]: ez <a>V</a> <span class='note'>om.</span> <a>W</a></span>" },
        { "01":"<span class='lem'>Plymizol</span> ] <span class='rdg'>plẏmizol <a>V</a> plimizol <a>W</a></span>" },
        { "02":"<span class='lem'>Melyanzes</span> ] <span class='rdg'>Melẏanzes <a>V</a> Melianzes <a>W</a></span>" },
        { "03":"<span class='lem'>Liz</span> ] <span class='rdg'>Lŷz <a>T</a> lẏs <a>V</a> lis <a>W</a></span>" },
        { "04":"<span class='lem'>sîner</span> ] <span class='rdg'>nam siner <a>V</a> (<a>W</a>)</span>" },
        { "05":"<span class='lem'>nam war</span> ] <span class='rdg'><span class='note'>om.</span> <a>V</a> <a>W</a></span>" },
        { "05":"<span class='lem'>Melyanzen</span> ] <span class='rdg'>melianzen <a>T</a> <a>W</a> melẏanzen <a>V</a></span>" },
        { "06":"<span class='lem'>Orestegentesin</span> ] <span class='rdg'>[*]: orastegentesin <a>V</a> arastegente sein <a>W</a></span>" },
        { "07-1":"<span class='rdg'><span class='note'>Die Verse 385.71-72 fehlen</span> <a>W</a></span>" },
        { "07-1":"<span class='lem'>getriben</span> ] <span class='rdg'>[*]: gezilt <a>V</a></span>" },
        { "08":"<span class='lem'>si brast</span> ] <span class='rdg'>[*]: er brast <a>V</a> erbrast <a>W</a></span>" },
        { "09":"<span class='lem'>geschach</span> ] <span class='rdg'>gescahc <a>T</a></span>" },
        { "10":"<span class='lem'>stach</span> ] <span class='rdg'>[*]: nider stach <a>V</a></span>" },
        { "11":"<span class='lem'>sînen</span> ] <span class='rdg'>den <a>W</a></span>" },
        { "12":"<span class='lem'>vür</span> ] <span class='rdg'>vil <a>V</a></span>" },
        { "13":"<span class='lem'>gestuonden</span> ] <span class='rdg'>stunden <a>W</a></span>" },
        { "14":"<span class='lem'>dô</span> ] <span class='rdg'>Da <a>V</a></span>" },
        { "14":"<span class='lem'>tâtens</span> ] <span class='rdg'>taten <a>W</a></span>" },
        { "16":"<span class='lem'>dâ</span> ] <span class='rdg'>Do <a>V</a> <a>W</a></span>" },
        { "18":"<span class='lem'>ietwedern</span> ] <span class='rdg'>Jewederre <a>V</a> (<a>W</a>)</span>" },
        { "18":"<span class='lem'>garbe</span> ] <span class='rdg'>grabe <a>T</a></span>" },
        { "18":"<span class='lem'>dar</span> ] <span class='rdg'><span class='note'>om.</span> <a>V</a> <a>W</a></span>" },
        { "19":"<span class='lem'>geslagen</span> ] <span class='rdg'>getragen <a>W</a></span>" },
        { "20":"<span class='lem'>Melyanz</span> ] <span class='rdg'>Melianz <a>V</a> Melyanß <a>W</a></span>" },
        { "22":"<span class='lem'>bluotic</span> ] <span class='rdg'>[B*]: Bluͦt vnde <a>V</a></span>" },
        { "22":"<span class='lem'>in</span> ] <span class='rdg'>[*]: im <a>V</a> im <a>W</a></span>" },
        { "24":"<span class='lem'>Prevegariez</span> ] <span class='rdg'>[*]: brevigariezer <a>V</a> breuegariessere <a>W</a></span>" },
        { "27":"<span class='lem'>wære</span> ] <span class='rdg'>[W*]: Were aber <a>V</a></span>" },
        { "28":"<span class='rdg'>[*]: Done were nieman so gohes kvnt <a>V</a></span>" },
        { "28":"<span class='rdg'>Danne wer so gahes niemant kunt <a>W</a></span>" },
        { "29":"<span class='lem'>im</span> ] <span class='rdg'>in <a>T</a></span>" },
        { "30":"<span class='lem'>sîn</span> ] <span class='rdg'>[*]: ez in <a>V</a> in es <a>W</a></span>" }
      ],
      "handle": "*T",
      "distribution": "<ul><li><a data-thirties=\"385\">T</a></li><li><a data-thirties=\"385\">V</a></li><li><a data-thirties=\"385\">W</a></li></ul>",
      "structure": [  ]
    }
  ],
  "meta": {
    "generated-by": "parzival-static-api/src/generate.xsl",
    "task": "metadata-syn-apps",
    "generated-on": "2026-02-02T20:32:21.639161207+01:00",
    "description": "Apparatus information (distribution, structural, readings)."
  }
}