{
  "versions": [
    {
      "reading": [
        { "07":"<span class='lem'>Scherules</span> ] <span class='rdg'>Scervles <a>D</a></span>" },
        { "17":"<span class='lem'>Liz</span> ] <span class='rdg'>Lŷz <a>D</a></span>" },
        { "30":"<span class='lem'>Lisavander</span> ] <span class='rdg'>Lysavandr <a>D</a></span>" }
      ],
      "handle": "*D",
      "distribution": "<ul><li><a data-thirties=\"380\">D</a></li></ul>",
      "structure": [
        { "01":"<span class='note'>Initiale</span> <a>D</a>" },
        { "25":"<span class='note'>Majuskel</span> <a>D</a>" }
      ]
    },
    {
      "reading": [
        { "01":"<span class='lem'>ersach</span> ] <span class='rdg'>er sach <a>m</a> <a>n</a> <a>o</a></span>" },
        { "01":"<span class='lem'>mîn hêr</span> ] <span class='rdg'>mẏnen herren <a>o</a></span>" },
        { "01":"<span class='lem'>Gawan</span> ] <span class='rdg'>gewan <a>m</a></span>" },
        { "02":"<span class='lem'>gevlohten</span> ] <span class='rdg'>geflockten <a>o</a></span>" },
        { "03":"<span class='lem'>die vriunt</span> ] <span class='rdg'>Der vint <a>n</a></span>" },
        { "03":"<span class='lem'>vîende</span> ] <span class='rdg'>vigenden <a>n</a></span>" },
        { "07":"<span class='lem'>Scherules</span> ] <span class='rdg'>Schirmes <a>m</a> <a>n</a> <a>o</a></span>" },
        { "09":"<span class='lem'>dâ</span> ] <span class='rdg'>do <a>m</a> <a>n</a> <a>o</a></span>" },
        { "13":"<span class='lem'>wære</span> ] <span class='rdg'>er <a>o</a></span>" },
        { "13":"<span class='lem'>dâ</span> ] <span class='rdg'>do <a>n</a> <a>o</a></span>" },
        { "13":"<span class='lem'>gegert</span> ] <span class='rdg'>begert <a>n</a> <a>o</a></span>" },
        { "14":"<span class='lem'>dâ</span> ] <span class='rdg'>Do <a>m</a> <a>n</a> <a>o</a></span>" },
        { "14":"<span class='lem'>erklenget</span> ] <span class='rdg'>er clinget <a>n</a></span>" },
        { "15":"<span class='lem'>wâren</span> ] <span class='rdg'>warem <a>m</a></span>" },
        { "15":"<span class='lem'>her</span> ] <span class='rdg'>[heren]: her <a>o</a></span>" },
        { "16":"<span class='lem'>ze wer</span> ] <span class='rdg'>sower <a>o</a></span>" },
        { "17":"<span class='lem'>Liz</span> ] <span class='rdg'>lisz <a>n</a> liesz <a>o</a></span>" },
        { "17":"<span class='lem'>von</span> ] <span class='rdg'>vor <a>n</a></span>" },
        { "17":"<span class='lem'>Gros</span> ] <span class='rdg'>grosz <a>n</a> gors <a>o</a></span>" },
        { "18":"<span class='lem'>manic</span> ] <span class='rdg'>magnig <a>o</a></span>" },
        { "19":"<span class='lem'>brâhte</span> ] <span class='rdg'>brocke <a>o</a></span>" },
        { "21":"<span class='lem'>iemen</span> ] <span class='rdg'>einen <a>m</a> ẏeman sú <a>n</a></span>" },
        { "21":"<span class='lem'>dâ</span> ] <span class='rdg'>dar <a>m</a> do <a>n</a> <a>o</a></span>" },
        { "22":"<span class='lem'>was dâ</span> ] <span class='rdg'>[do]: was do <a>n</a> wasz do <a>o</a></span>" },
        { "22":"<span class='lem'>die sprâchen jâ</span> ] <span class='rdg'>gesprochen dar <a>m</a></span>" },
        { "23":"<span class='lem'>wurden</span> ] <span class='rdg'>wurde <a>o</a></span>" },
        { "23":"<span class='lem'>gelîche</span> ] <span class='rdg'>gliche [siner] <a>o</a></span>" },
        { "26":"<span class='lem'>sper</span> ] <span class='rdg'>sprer <a>m</a></span>" },
        { "27":"<span class='lem'>laschahtelis</span> ] <span class='rdg'>Laschathelún <a>n</a> Laschahtelún <a>o</a></span>" },
        { "27":"<span class='lem'>Beavois</span> ] <span class='rdg'>branois <a>m</a> <a>n</a> beanois <a>o</a></span>" },
        { "28":"<span class='lem'>der</span> ] <span class='rdg'>de <a>m</a> <a>n</a> <a>o</a></span>" },
        { "28":"<span class='lem'>kurtois</span> ] <span class='rdg'>turtois <a>n</a> tortonis <a>o</a></span>" },
        { "30":"<span class='lem'>Lisavander</span> ] <span class='rdg'>lisavanfander <a>m</a> lisarander <a>n</a> <a>o</a></span>" }
      ],
      "handle": "*m",
      "distribution": "<ul><li><a data-thirties=\"380\">m</a></li><li><a data-thirties=\"380\">n</a></li><li><a data-thirties=\"380\">o</a></li></ul>",
      "structure": [ { "01":"<span class='note'>Initiale</span> <a>m</a> <a>n</a> <a>o</a>" } ]
    },
    {
      "reading": [
        { "01":"<span class='rdg'><span class='note'>Die Verse 370.13-412.12 fehlen</span> <a>Q</a></span>" },
        { "01":"<span class='lem'>nû</span> ] <span class='rdg'>÷v <a>O</a> Hv <a>M</a></span>" },
        { "01":"<span class='lem'>mîn</span> ] <span class='rdg'><span class='note'>om.</span> <a>R</a></span>" },
        { "02":"<span class='lem'>gevlohten</span> ] <span class='rdg'>vlochtin <a>M</a></span>" },
        { "03":"<span class='lem'>in der</span> ] <span class='rdg'>vnder <a>G</a></span>" },
        { "04":"<span class='lem'>ouch sich</span> ] <span class='rdg'>sich ouch <a>M</a> ich och <a>R</a></span>" },
        { "04":"<span class='lem'>des endes</span> ] <span class='rdg'>mit poynder <a>O</a> (<a>L</a> <a>Z</a> <a>Fr21</a>) mit poynde <a>M</a> mit strite <a>R</a></span>" },
        { "05":"<span class='lem'>was sîn</span> ] <span class='rdg'>si was <a>O</a> sin waz <a>L</a> (<a>M</a> <a>R</a> <a>Z</a> <a>Fr21</a>)</span>" },
        { "06":"<span class='lem'>dô</span> ] <span class='rdg'>da <a>M</a> <a>Z</a> er <a>R</a></span>" },
        { "06":"<span class='lem'>sparten</span> ] <span class='rdg'>gesparten <a>O</a> <a>L</a> (<a>M</a>) sparte <a>R</a></span>" },
        { "07":"<span class='lem'>Tscherules</span> ] <span class='rdg'>Scurles <a>I</a> Tschervles <a>O</a> <a>Fr21</a> Thervles <a>L</a> Scerules <a>M</a> Therules <a>R</a> </span>" },
        { "07":"<span class='lem'>die</span> ] <span class='rdg'>alle die <a>I</a> (<a>M</a>) <a>R</a> (<a>Z</a> <a>Fr21</a>)</span>" },
        { "07":"<span class='lem'>sîne</span> ] <span class='rdg'>sinen <a>R</a></span>" },
        { "08":"<span class='lem'>pîne</span> ] <span class='rdg'>pinen <a>R</a></span>" },
        { "09":"<span class='lem'>dâ</span> ] <span class='rdg'>do <a>O</a> <a>R</a></span>" },
        { "09":"<span class='lem'>stach</span> ] <span class='rdg'>[sprach]: :prach <a>Z</a></span>" },
        { "10":"<span class='lem'>waz</span> ] <span class='rdg'>vnde waz <a>O</a> (<a>L</a> <a>M</a> <a>R</a> <a>Z</a> <a>Fr21</a>)</span>" },
        { "10":"<span class='lem'>dâ</span> ] <span class='rdg'><span class='note'>om.</span> <a>O</a> <a>L</a> <a>R</a> <a>Z</a> <a>Fr21</a></span>" },
        { "10":"<span class='lem'>zerbrach</span> ] <span class='rdg'>zv stach <a>Z</a></span>" },
        { "11":"<span class='lem'>der</span> ] <span class='rdg'>die <a>I</a></span>" },
        { "11":"<span class='lem'>werde</span> ] <span class='rdg'>werden <a>L</a> <a>Z</a></span>" },
        { "11":"<span class='lem'>tavelrunde</span> ] <span class='rdg'>Tauelrunder <a>I</a> (<a>O</a> <a>M</a> <a>R</a> <a>Z</a> <a>Fr21</a>)</span>" },
        { "12":"<span class='lem'>die</span> ] <span class='rdg'>der <a>Fr21</a></span>" },
        { "12":"<span class='lem'>niht von</span> ] <span class='rdg'>[vor]: von <a>M</a></span>" },
        { "13":"<span class='lem'>dâ</span> ] <span class='rdg'>do <a>R</a></span>" },
        { "13":"<span class='lem'>prîs</span> ] <span class='rdg'>prises <a>L</a> <a>R</a></span>" },
        { "14":"<span class='lem'>dâ</span> ] <span class='rdg'>Do <a>R</a></span>" },
        { "14":"<span class='lem'>erklenget</span> ] <span class='rdg'>erzogn <a>Fr21</a></span>" },
        { "15":"<span class='lem'>im</span> ] <span class='rdg'>Jn <a>Fr21</a></span>" },
        { "15":"<span class='lem'>aleine</span> ] <span class='rdg'>gelic <a>G</a> allu <a>R</a></span>" },
        { "17":"<span class='lem'>Liz</span> ] <span class='rdg'>lis <a>I</a> lýz <a>L</a> lisz <a>M</a> Loys <a>R</a> liez <a>Z</a> </span>" },
        { "17":"<span class='lem'>Gors</span> ] <span class='rdg'>Goͤrse <a>O</a> Gorsz <a>L</a> gorcz <a>M</a> Goͤrss <a>Z</a> </span>" },
        { "18":"<span class='lem'>von beider sîte</span> ] <span class='rdg'>[*]: zebeider siten <a>I</a> Von beiden sitten <a>R</a></span>" },
        { "18":"<span class='lem'>er</span> ] <span class='rdg'><span class='note'>om.</span> <a>Z</a></span>" },
        { "18":"<span class='lem'>manic</span> ] <span class='rdg'>mangen <a>G</a></span>" },
        { "19":"<span class='lem'>gezogen</span> ] <span class='rdg'>Er gezogen <a>Z</a></span>" },
        { "19":"<span class='lem'>brâhte</span> ] <span class='rdg'>brahter <a>I</a></span>" },
        { "21":"<span class='lem'>vrâgte</span> ] <span class='rdg'>fragt <a>I</a> <a>O</a> <a>Fr21</a></span>" },
        { "25":"<span class='lem'>her</span> ] <span class='rdg'>dar <a>I</a></span>" },
        { "26":"<span class='lem'>sper</span> ] <span class='rdg'>spern <a>R</a></span>" },
        { "26":"<span class='lem'>kunde</span> ] <span class='rdg'><span class='note'>om.</span> <a>Z</a></span>" },
        { "27":"<span class='rdg'><span class='note'>Versfolge 380.28-27</span> <a>I</a></span>" },
        { "27":"<span class='lem'>der</span> ] <span class='rdg'>vnde der <a>I</a></span>" },
        { "27":"<span class='lem'>von</span> ] <span class='rdg'><span class='note'>om.</span> <a>I</a></span>" },
        { "27":"<span class='lem'>Beavoys</span> ] <span class='rdg'>beauoys <a>G</a> beafoys <a>I</a> Beavoẏs <a>O</a> Beaveis <a>L</a> beareis <a>R</a> Bearoys <a>Fr21</a> </span>" },
        { "29":"<span class='lem'>die</span> ] <span class='rdg'><span class='note'>om.</span> <a>Z</a></span>" },
        { "29":"<span class='lem'>ein</span> ] <span class='rdg'>an <a>I</a></span>" },
        { "30":"<span class='lem'>Lisavander</span> ] <span class='rdg'>lisauander <a>G</a> lisamander <a>I</a> Liswander <a>O</a> Lýsavander <a>L</a> lisavandir <a>M</a> Lysavander <a>R</a> <a>Z</a> ::: <a>Fr21</a> </span>" }
      ],
      "handle": "*G",
      "distribution": "<ul><li><a data-thirties=\"380\">G</a></li><li><a data-thirties=\"380\">I</a></li><li><a data-thirties=\"380\">O</a></li><li><a data-thirties=\"380\">L</a></li><li><a data-thirties=\"380\">M</a></li><li><a data-thirties=\"380\">Q</a></li><li><a data-thirties=\"380\">R</a></li><li><a data-thirties=\"380\">Z</a></li><li><a data-thirties=\"380\">Fr21</a></li></ul>",
      "structure": [
        { "01":"<span class='note'>Initiale</span> <a>I</a> <a>O</a> <a>L</a> <a>M</a> <a>Z</a> <a>Fr21</a>" },
        { "01":"<span class='note'>Capitulumzeichen</span> <a>R</a>" },
        { "09":"<span class='note'>Initiale</span> <a>G</a>" },
        { "15":"<span class='note'>Initiale</span> <a>I</a>" }
      ]
    },
    {
      "reading": [
        { "01":"<span class='lem'>Dô</span> ] <span class='rdg'>NVn <a>W</a></span>" },
        { "04":"<span class='lem'>ouch</span> ] <span class='rdg'>oͮch sich <a>V</a> (<a>W</a>)</span>" },
        { "04":"<span class='lem'>poynder</span> ] <span class='rdg'>poyndier <a>T</a></span>" },
        { "06":"<span class='lem'>si</span> ] <span class='rdg'>do <a>W</a></span>" },
        { "07":"<span class='lem'>Tscherules</span> ] <span class='rdg'>Schervles <a>V</a> Descherules <a>W</a> </span>" },
        { "08":"<span class='rdg'><span class='note'>Vers 380.8 fehlt (Zeile ausgespart)</span> <a>T</a></span>" },
        { "09":"<span class='lem'>dâ</span> ] <span class='rdg'>do <a>V</a> <a>W</a></span>" },
        { "10":"<span class='lem'>er</span> ] <span class='rdg'>er do <a>W</a></span>" },
        { "11":"<span class='lem'>werden</span> ] <span class='rdg'>werde <a>W</a></span>" },
        { "13":"<span class='lem'>dâ prîs</span> ] <span class='rdg'>do pris <a>V</a> do peises <a>W</a></span>" },
        { "14":"<span class='lem'>dâ</span> ] <span class='rdg'>Do <a>V</a> <a>W</a></span>" },
        { "17":"<span class='lem'>Lyz</span> ] <span class='rdg'>Lŷz <a>T</a> lis <a>V</a> <a>W</a></span>" },
        { "17":"<span class='lem'>Gors</span> ] <span class='rdg'>gorß <a>W</a></span>" },
        { "18":"<span class='lem'>er</span> ] <span class='rdg'><span class='note'>om.</span> <a>T</a></span>" },
        { "21":"<span class='lem'>si ob</span> ] <span class='rdg'>ob sv́ <a>V</a> (<a>W</a>)</span>" },
        { "21":"<span class='lem'>dâ</span> ] <span class='rdg'>do <a>V</a></span>" },
        { "22":"<span class='lem'>ir was</span> ] <span class='rdg'>Ja <a>V</a></span>" },
        { "25":"<span class='lem'>Dô</span> ] <span class='rdg'>Dv <a>T</a> Nv <a>V</a> (<a>W</a>)</span>" },
        { "26":"<span class='lem'>diu</span> ] <span class='rdg'>der <a>V</a></span>" },
        { "27":"<span class='lem'>Beavoys</span> ] <span class='rdg'>Beavôys <a>T</a> Beavoẏs <a>V</a> beaueis <a>W</a></span>" },
        { "30":"<span class='lem'>Lysavander</span> ] <span class='rdg'>lẏsavander <a>V</a> lysauander <a>W</a></span>" }
      ],
      "handle": "*T",
      "distribution": "<ul><li><a data-thirties=\"380\">T</a></li><li><a data-thirties=\"380\">V</a></li><li><a data-thirties=\"380\">W</a></li></ul>",
      "structure": [
        { "01":"<span class='note'>Initiale</span> <a>W</a>" },
        { "01":"<span class='note'>Majuskel</span> <a>T</a>" },
        { "25":"<span class='note'>Initiale</span> <a>T</a>" }
      ]
    }
  ],
  "meta": {
    "generated-by": "parzival-static-api/src/generate.xsl",
    "task": "metadata-syn-apps",
    "generated-on": "2025-08-22T15:23:12.977848529+02:00",
    "description": "Apparatus information (distribution, structural, readings)."
  }
}