{
  "versions": [
    {
      "reading": [
        { "02":"<span class='lem'>tæte</span> ] <span class='rdg'>tut <a>Z</a></span>" },
        { "03":"<span class='lem'>rüemen</span> ] <span class='rdg'>rvm <a>Z</a></span>" },
        { "03":"<span class='lem'>liep</span> ] <span class='rdg'>lip <a>D</a> [lop]: liep <a>Z</a></span>" },
        { "04":"<span class='lem'>sip</span> ] <span class='rdg'>schiep <a>Z</a></span>" },
        { "10":"<span class='lem'>getörst</span> ] <span class='rdg'>getorst <a>D</a> <a>Z</a></span>" },
        { "14":"<span class='lem'>herzoginne</span> ] <span class='rdg'>kuniginne <a>Z</a></span>" },
        { "16":"<span class='lem'>hie</span> ] <span class='rdg'><span class='note'>om.</span> <a>Z</a></span>" },
        { "18":"<span class='lem'>mîn dienst ruochet</span> ] <span class='rdg'>minen dienst geruchet <a>Z</a></span>" },
        { "22":"<span class='lem'>mêr</span> ] <span class='rdg'>Vnd mer <a>Z</a></span>" },
        { "23":"<span class='lem'>mir</span> ] <span class='rdg'>mit <a>Z</a></span>" },
        { "26":"<span class='lem'>Turkoten</span> ] <span class='rdg'>Tvrkoiten <a>Z</a></span>" },
        { "27":"<span class='lem'>mit</span> ] <span class='rdg'>Bi <a>Z</a></span>" },
        { "27":"<span class='lem'>Plippalinot</span> ] <span class='rdg'>plipalinot <a>Z</a></span>" },
        { "29":"<span class='rdg'><span class='note'>Versfolge 599.30-29</span> <a>Z</a></span>" },
        { "29":"<span class='lem'>sîn</span> ] <span class='rdg'>sie sin <a>Z</a></span>" },
        { "30":"<span class='lem'>die</span> ] <span class='rdg'>den <a>Z</a></span>" }
      ],
      "handle": "*D",
      "distribution": "<ul><li><a data-thirties=\"599\">D</a></li><li><a data-thirties=\"599\">Z</a></li></ul>",
      "structure": [
        { "01":"<span class='note'>Initiale</span> <a>D</a>" },
        { "05":"<span class='note'>Initiale</span> <a>Z</a>" },
        { "09":"<span class='note'>Majuskel</span> <a>D</a>" },
        { "14":"<span class='note'>Majuskel</span> <a>D</a>" },
        { "21":"<span class='note'>Majuskel</span> <a>D</a>" }
      ]
    },
    {
      "reading": [
        { "03":"<span class='lem'>wesen</span> ] <span class='rdg'>wen <a>o</a></span>" },
        { "04":"<span class='lem'>dürkelt</span> ] <span class='rdg'>durchkelt <a>m</a></span>" },
        { "05":"<span class='lem'>sô</span> ] <span class='rdg'>do <a>n</a></span>" },
        { "07":"<span class='lem'>möht</span> ] <span class='rdg'>Moht <a>m</a> (<a>o</a>)</span>" },
        { "09":"<span class='lem'>rîtet</span> ] <span class='rdg'>Riten <a>o</a></span>" },
        { "10":"<span class='lem'>getörstet</span> ] <span class='rdg'>gestorstet <a>m</a> getursten <a>n</a></span>" },
        { "14":"<span class='lem'>herzoginne</span> ] <span class='rdg'>herczoginnen <a>o</a></span>" },
        { "18":"<span class='lem'>ruochet</span> ] <span class='rdg'>rúchen <a>n</a></span>" },
        { "19":"<span class='lem'>nie</span> ] <span class='rdg'>mẏe <a>m</a></span>" },
        { "24":"<span class='lem'>des</span> ] <span class='rdg'>Das <a>o</a></span>" },
        { "24":"<span class='lem'>vröuden</span> ] <span class='rdg'>freiuden <a>o</a></span>" },
        { "26":"<span class='lem'>Turkoiten</span> ] <span class='rdg'>kurtoitten <a>m</a> (<a>n</a>) kortoiten <a>o</a></span>" },
        { "26":"<span class='lem'>santer</span> ] <span class='rdg'>snitter <a>m</a></span>" },
        { "27":"<span class='lem'>Plippalinot</span> ] <span class='rdg'>plippolmot <a>m</a> <a>n</a> plippolinat <a>o</a></span>" },
        { "29":"<span class='lem'>mit</span> ] <span class='rdg'>nit <a>o</a></span>" }
      ],
      "handle": "*m",
      "distribution": "<ul><li><a data-thirties=\"599\">m</a></li><li><a data-thirties=\"599\">n</a></li><li><a data-thirties=\"599\">o</a></li></ul>",
      "structure": [  ]
    },
    {
      "reading": [
        { "03":"<span class='lem'>wol</span> ] <span class='rdg'><span class='note'>om.</span> <a>L</a> <a>M</a> <a>Z</a></span>" },
        { "03":"<span class='lem'>liep</span> ] <span class='rdg'>[lop]: liep <a>Z</a></span>" },
        { "04":"<span class='lem'>schilt</span> ] <span class='rdg'>shilt ist <a>I</a></span>" },
        { "04":"<span class='lem'>sip</span> ] <span class='rdg'>schiep <a>Z</a></span>" },
        { "05":"<span class='lem'>brach</span> ] <span class='rdg'>durc [bl]: brach <a>I</a> zerbrach <a>L</a> (<a>M</a> <a>Z</a>)</span>" },
        { "07":"<span class='lem'>daz</span> ] <span class='rdg'><span class='note'>om.</span> <a>L</a> <a>Z</a></span>" },
        { "09":"<span class='lem'>rîtet</span> ] <span class='rdg'><span class='note'>om.</span> <a>I</a></span>" },
        { "09":"<span class='lem'>ûf</span> ] <span class='rdg'><span class='note'>om.</span> <a>I</a></span>" },
        { "10":"<span class='lem'>saget</span> ] <span class='rdg'><span class='note'>om.</span> <a>Z</a></span>" },
        { "10":"<span class='lem'>getörst ir</span> ] <span class='rdg'>getorst ir <a>G</a> <a>L</a> <a>Z</a> [gerst]: getorst <a>I</a> gesi tostir <a>M</a></span>" },
        { "10":"<span class='lem'>schouwen</span> ] <span class='rdg'>ie beshawen <a>I</a> geschouwen <a>M</a> <a>Z</a></span>" },
        { "13":"<span class='lem'>minne</span> ] <span class='rdg'>mýnnen <a>L</a> (<a>M</a>)</span>" },
        { "14":"<span class='lem'>küneginne</span> ] <span class='rdg'>hertzoginen <a>L</a> (<a>M</a>)</span>" },
        { "15":"<span class='lem'>ich hân</span> ] <span class='rdg'>han ich <a>L</a> <a>M</a> <a>Z</a></span>" },
        { "15":"<span class='lem'>wunden</span> ] <span class='rdg'>funden <a>G</a></span>" },
        { "16":"<span class='lem'>vunden</span> ] <span class='rdg'>wunden <a>G</a> enphunden <a>I</a></span>" },
        { "17":"<span class='lem'>helfe</span> ] <span class='rdg'><span class='note'>om.</span> <a>G</a> ewer helfe <a>Z</a></span>" },
        { "18":"<span class='lem'>geruochet</span> ] <span class='rdg'>ruͤchet <a>I</a> (<a>L</a>) geruget <a>M</a></span>" },
        { "19":"<span class='lem'>sône</span> ] <span class='rdg'>So <a>Z</a></span>" },
        { "20":"<span class='lem'>dar</span> ] <span class='rdg'>ev dar <a>Z</a></span>" },
        { "22":"<span class='lem'>prîse</span> ] <span class='rdg'>[strite]: prise <a>I</a></span>" },
        { "23":"<span class='lem'>mir</span> ] <span class='rdg'>mit <a>Z</a></span>" },
        { "24":"<span class='lem'>wart an</span> ] <span class='rdg'>anden <a>M</a></span>" },
        { "26":"<span class='lem'>den Turkoiten</span> ] <span class='rdg'>lyshoisen <a>G</a> den Turchoyden <a>I</a> Lýtschosen <a>L</a> Lysoien <a>M</a></span>" },
        { "26":"<span class='lem'>sân</span> ] <span class='rdg'>dan <a>L</a> <a>Z</a> soen <a>M</a></span>" },
        { "27":"<span class='lem'>Pliplalinot</span> ] <span class='rdg'>plipalinot <a>I</a> <a>L</a> <a>M</a> <a>Z</a></span>" },
        { "30":"<span class='lem'>den</span> ] <span class='rdg'>Nach den <a>G</a> Al den <a>L</a> (<a>M</a>) <a>Z</a></span>" },
        { "29":"<span class='lem'>sis</span> ] <span class='rdg'>si sin <a>I</a> (<a>Z</a>)</span>" },
        { "29":"<span class='lem'>mit wirden</span> ] <span class='rdg'><span class='note'>om.</span> <a>I</a> mit wirde <a>L</a> <a>Z</a></span>" },
        { "29":"<span class='lem'>næmen</span> ] <span class='rdg'>nemen wol <a>I</a> namen <a>L</a></span>" }
      ],
      "handle": "*G",
      "distribution": "<ul><li><a data-thirties=\"599\">G</a></li><li><a data-thirties=\"599\">I</a></li><li><a data-thirties=\"599\">L</a></li><li><a data-thirties=\"599\">M</a></li><li><a data-thirties=\"599\">Z</a></li></ul>",
      "structure": [
        { "05":"<span class='note'>Initiale</span> <a>I</a> <a>L</a> <a>M</a> <a>Z</a>" },
        { "21":"<span class='note'>Initiale</span> <a>I</a>" }
      ]
    },
    {
      "reading": [
        { "01":"<span class='rdg'><span class='note'>Die Verse 553.1-599.30 fehlen</span> <a>U</a></span>" },
        { "04":"<span class='lem'>dürkel</span> ] <span class='rdg'>dunckel <a>R</a> dúrckelt <a>W</a> [dunkelt]: durkel <a>V</a></span>" },
        { "05":"<span class='lem'>pfîl</span> ] <span class='rdg'>pfeyle <a>Q</a></span>" },
        { "10":"<span class='rdg'>[*]: Wie getorstent ir geschowe <a>V</a></span>" },
        { "10":"<span class='lem'>getörst</span> ] <span class='rdg'>getorst <a>Q</a> <a>R</a> (<a>V</a>)</span>" },
        { "13":"<span class='lem'>minne</span> ] <span class='rdg'>mine <a>W</a></span>" },
        { "15":"<span class='lem'>vrou</span> ] <span class='rdg'>Erawe <a>W</a></span>" },
        { "16":"<span class='lem'>vunden</span> ] <span class='rdg'>[*]: hie fvnden <a>V</a></span>" },
        { "17":"<span class='lem'>iuch</span> ] <span class='rdg'>[*]: uwer <a>V</a></span>" },
        { "17":"<span class='lem'>kan</span> ] <span class='rdg'>mag <a>R</a> [*]: kan <a>V</a></span>" },
        { "18":"<span class='lem'>mîn dienst</span> ] <span class='rdg'>nun hilffe <a>W</a> minen dienst <a>V</a></span>" },
        { "18":"<span class='lem'>geruochet</span> ] <span class='rdg'>geruͦchen <a>R</a></span>" },
        { "19":"<span class='lem'>wart</span> ] <span class='rdg'>enwart <a>R</a> (<a>W</a>) <a>V</a></span>" },
        { "20":"<span class='lem'>ichn</span> ] <span class='rdg'>Jch <a>R</a> (<a>W</a>)</span>" },
        { "20":"<span class='lem'>dar benant</span> ] <span class='rdg'>dar benam <a>Q</a> [*]: v́ch dar benant <a>V</a></span>" },
        { "24":"<span class='lem'>rîche</span> ] <span class='rdg'>reichen <a>Q</a></span>" },
        { "25":"<span class='lem'>Gawan</span> ] <span class='rdg'>gewan <a>R</a> </span>" },
        { "26":"<span class='lem'>Turkoyten</span> ] <span class='rdg'>turkoiten <a>Q</a> tvrkorten <a>V</a> </span>" },
        { "26":"<span class='lem'>sant er</span> ] <span class='rdg'>er sante <a>V</a></span>" },
        { "30":"<span class='lem'>al den</span> ] <span class='rdg'>Allen <a>R</a> <a>W</a></span>" },
        { "29":"<span class='lem'>sis mit</span> ] <span class='rdg'>sies nit <a>R</a> sir mit <a>W</a> sv́ sin mit <a>V</a></span>" },
        { "29":"<span class='lem'>wirden</span> ] <span class='rdg'>wirde <a>W</a> (<a>V</a>)</span>" }
      ],
      "handle": "*T",
      "distribution": "<ul><li><a data-thirties=\"599\">Q</a></li><li><a data-thirties=\"599\">R</a></li><li><a data-thirties=\"599\">W</a></li><li><a data-thirties=\"599\">V</a></li><li><a data-thirties=\"599\">U</a></li></ul>",
      "structure": [
        { "05":"<span class='note'>Capitulumzeichen</span> <a>R</a>" },
        { "21":"<span class='note'>Initiale</span> <a>V</a>" }
      ]
    }
  ],
  "meta": {
    "generated-by": "parzival-static-api/src/generate.xsl",
    "task": "metadata-syn-apps",
    "generated-on": "2026-02-02T20:32:21.639161207+01:00",
    "description": "Apparatus information (distribution, structural, readings)."
  }
}