{
  "versions": [
    {
      "reading": [
        { "02":"<span class='lem'>senfte</span> ] <span class='rdg'>senftet <a>Fr7</a></span>" },
        { "03":"<span class='lem'>müese ir minne</span> ] <span class='rdg'>mvͦse ir minne <a>D</a> im ir minne muͦse <a>Fr7</a> m:s ir mynne <a>Fr11</a></span>" },
        { "04":"<span class='lem'>swaz</span> ] <span class='rdg'>swa <a>Fr11</a></span>" },
        { "04":"<span class='lem'>was von im</span> ] <span class='rdg'>von im was <a>Fr7</a> waz von ir <a>Fr11</a></span>" },
        { "05":"<span class='lem'>unt</span> ] <span class='rdg'>von <a>Fr7</a></span>" },
        { "05":"<span class='lem'>ir clârem</span> ] <span class='rdg'>ir claren <a>Fr7</a> (<a>Fr11</a>)</span>" },
        { "07":"<span class='lem'>kœme in herzenôt</span> ] <span class='rdg'>chom in herzn not <a>Fr11</a></span>" },
        { "08":"<span class='lem'>dâ nâch ir</span> ] <span class='rdg'>si dar nach r <a>Fr11</a></span>" },
        { "09":"<span class='lem'>tuot ez</span> ] <span class='rdg'>muͤz <a>Fr7</a></span>" },
        { "13":"<span class='lem'>keinen</span> ] <span class='rdg'>Ye <a>Fr11</a></span>" },
        { "14":"<span class='lem'>mir</span> ] <span class='rdg'>mit <a>Fr7</a></span>" },
        { "15":"<span class='lem'>site</span> ] <span class='rdg'>sin <a>Fr11</a></span>" },
        { "17":"<span class='lem'>die</span> ] <span class='rdg'>div <a>Fr7</a> (<a>Fr11</a>)</span>" },
        { "19":"<span class='lem'>kinde</span> ] <span class='rdg'>kinden <a>Fr7</a></span>" },
        { "20":"<span class='lem'>ie</span> ] <span class='rdg'>nie <a>Fr31</a></span>" },
        { "20":"<span class='lem'>ir</span> ] <span class='rdg'>im <a>Fr7</a></span>" },
        { "20":"<span class='lem'>vlôch</span> ] <span class='rdg'>gevloch <a>Fr31</a></span>" },
        { "21":"<span class='lem'>hülfe</span> ] <span class='rdg'>half <a>Fr7</a></span>" },
        { "22":"<span class='lem'>die juncvrouwen</span> ] <span class='rdg'>div ivnchfroͮwe <a>D</a> (<a>Fr11</a>)</span>" },
        { "22":"<span class='lem'>sprach</span> ] <span class='rdg'>gesprach <a>Fr11</a> <a>Fr31</a></span>" },
        { "23":"<span class='lem'>die</span> ] <span class='rdg'>div̽ <a>Fr11</a></span>" },
        { "24":"<span class='lem'>muose</span> ] <span class='rdg'>muͤse <a>Fr7</a> mu̽st <a>Fr11</a></span>" },
        { "27":"<span class='lem'>ez</span> ] <span class='rdg'>Er <a>Fr31</a></span>" },
        { "30":"<span class='lem'>diu</span> ] <span class='rdg'>di <a>Fr11</a></span>" },
        { "30":"<span class='lem'>gerochen</span> ] <span class='rdg'>errochen <a>Fr31</a></span>" }
      ],
      "handle": "*D",
      "distribution": "<ul><li><a data-thirties=\"528\">D</a></li><li><a data-thirties=\"528\">Fr7</a> <span>(528.1-24)</span></li><li><a data-thirties=\"528\">Fr11</a></li><li><a data-thirties=\"528\">Fr31</a> <span>(528.16-30)</span></li></ul>",
      "structure": [
        { "01":"<span class='note'>Initiale</span> <a>D</a>" },
        { "11":"<span class='note'>Majuskel</span> <a>D</a>" },
        { "17":"<span class='note'>Initiale</span> <a>Fr11</a>" },
        { "17":"<span class='note'>Majuskel</span> <a>D</a>" },
        { "23":"<span class='note'>Majuskel</span> <a>D</a>" }
      ]
    },
    {
      "reading": [
        { "02":"<span class='lem'>senfter</span> ] <span class='rdg'>Senffteret <a>n</a> Senfftent <a>o</a></span>" },
        { "03":"<span class='lem'>müeste</span> ] <span class='rdg'>muͦste <a>o</a></span>" },
        { "03":"<span class='lem'>jehen</span> ] <span class='rdg'>sehen <a>o</a></span>" },
        { "04":"<span class='lem'>dâ</span> ] <span class='rdg'>do <a>m</a> <a>n</a> <a>o</a></span>" },
        { "05":"<span class='lem'>ir clâren</span> ] <span class='rdg'>irem clorem <a>n</a></span>" },
        { "09":"<span class='lem'>tuot</span> ] <span class='rdg'>duͦnt <a>n</a></span>" },
        { "11":"<span class='lem'>sîne</span> ] <span class='rdg'>sin <a>m</a> <a>n</a> <a>o</a></span>" },
        { "13":"<span class='lem'>kein</span> ] <span class='rdg'>Keinen <a>n</a> <a>o</a></span>" },
        { "18":"<span class='lem'>sippe minne</span> ] <span class='rdg'>die sippe min <a>n</a></span>" },
        { "20":"<span class='lem'>ir</span> ] <span class='rdg'>in <a>o</a></span>" },
        { "22":"<span class='lem'>juncvrouwen</span> ] <span class='rdg'>jungfrouwe <a>m</a> <a>n</a> (<a>o</a>)</span>" },
        { "24":"<span class='lem'>muos</span> ] <span class='rdg'>mu̽sz <a>n</a></span>" },
        { "26":"<span class='lem'>solich</span> ] <span class='rdg'>Solliche <a>n</a></span>" },
        { "27":"<span class='lem'>ez</span> ] <span class='rdg'>Er <a>n</a></span>" },
        { "27":"<span class='lem'>wær</span> ] <span class='rdg'><span class='note'>om.</span> <a>o</a></span>" },
        { "27":"<span class='lem'>vorlouf</span> ] <span class='rdg'>verlouff <a>m</a> <a>n</a> (<a>o</a>)</span>" },
        { "29":"<span class='lem'>in dâ</span> ] <span class='rdg'>do <a>m</a> in do <a>n</a> (<a>o</a>)</span>" }
      ],
      "handle": "*m",
      "distribution": "<ul><li><a data-thirties=\"528\">m</a></li><li><a data-thirties=\"528\">n</a></li><li><a data-thirties=\"528\">o</a></li></ul>",
      "structure": [  ]
    },
    {
      "reading": [
        { "01":"<span class='lem'>Daz</span> ] <span class='rdg'>Was <a>M</a></span>" },
        { "02":"<span class='lem'>senfte</span> ] <span class='rdg'>senftet <a>I</a> Sempftert <a>L</a></span>" },
        { "03":"<span class='lem'>daz</span> ] <span class='rdg'>daz sý <a>L</a> (<a>M</a> <a>Z</a>)</span>" },
        { "03":"<span class='lem'>müese</span> ] <span class='rdg'>muse <a>I</a> must <a>Z</a></span>" },
        { "03":"<span class='lem'>jehen</span> ] <span class='rdg'>ier <a>M</a></span>" },
        { "04":"<span class='lem'>swaz</span> ] <span class='rdg'>Waz <a>L</a> (<a>M</a>)</span>" },
        { "04":"<span class='lem'>was</span> ] <span class='rdg'>waz von ým <a>L</a> (<a>M</a> <a>Z</a>)</span>" },
        { "05":"<span class='lem'>ir clârem</span> ] <span class='rdg'>ir claren <a>L</a> (<a>M</a>)</span>" },
        { "06":"<span class='lem'>ob</span> ] <span class='rdg'><span class='note'>om.</span> <a>G</a></span>" },
        { "07":"<span class='lem'>mit</span> ] <span class='rdg'>Von <a>M</a></span>" },
        { "07":"<span class='lem'>kœme</span> ] <span class='rdg'>chom <a>I</a> (<a>L</a>)</span>" },
        { "07":"<span class='lem'>in herzenôt</span> ] <span class='rdg'>in herzen not <a>I</a> ir herte not <a>L</a> inherte not <a>M</a></span>" },
        { "11":"<span class='lem'>bat</span> ] <span class='rdg'>mant <a>Z</a></span>" },
        { "12":"<span class='lem'>ich im</span> ] <span class='rdg'>ich in <a>G</a> yme <a>M</a></span>" },
        { "13":"<span class='lem'>ers</span> ] <span class='rdg'>er sin <a>I</a></span>" },
        { "13":"<span class='lem'>gedæhte</span> ] <span class='rdg'>gedahte <a>G</a> <a>L</a></span>" },
        { "14":"<span class='lem'>mir lasters</span> ] <span class='rdg'>mins lasters iht <a>I</a> mir laster <a>M</a></span>" },
        { "18":"<span class='lem'>bat</span> ] <span class='rdg'>Gap <a>Z</a></span>" },
        { "20":"<span class='lem'>ie</span> ] <span class='rdg'><span class='note'>om.</span> <a>I</a></span>" },
        { "21":"<span class='lem'>geschach</span> ] <span class='rdg'>[gesach]: geshach <a>I</a></span>" },
        { "22":"<span class='lem'>sprach</span> ] <span class='rdg'>do gesprach <a>I</a></span>" },
        { "23":"<span class='lem'>dô</span> ] <span class='rdg'>Da <a>M</a></span>" },
        { "24":"<span class='lem'>muose</span> ] <span class='rdg'>muese <a>G</a> (<a>I</a>)</span>" },
        { "24":"<span class='lem'>hôhen</span> ] <span class='rdg'>hohe <a>L</a></span>" },
        { "25":"<span class='lem'>lîp</span> ] <span class='rdg'><span class='note'>om.</span> <a>Z</a></span>" },
        { "26":"<span class='lem'>im</span> ] <span class='rdg'>wart im <a>I</a></span>" },
        { "27":"<span class='lem'>ez</span> ] <span class='rdg'>[Er]: Ez <a>G</a></span>" },
        { "27":"<span class='lem'>vorlouft</span> ] <span class='rdg'>vorlovs <a>L</a></span>" },
        { "28":"<span class='lem'>sîn</span> ] <span class='rdg'>sine <a>G</a></span>" },
        { "30":"<span class='lem'>gerochen</span> ] <span class='rdg'>errochen <a>I</a></span>" }
      ],
      "handle": "*G",
      "distribution": "<ul><li><a data-thirties=\"528\">G</a></li><li><a data-thirties=\"528\">I</a></li><li><a data-thirties=\"528\">L</a></li><li><a data-thirties=\"528\">M</a></li><li><a data-thirties=\"528\">Z</a></li></ul>",
      "structure": [ { "01":"<span class='note'>Initiale</span> <a>G</a> <a>L</a> <a>Z</a>" } ]
    },
    {
      "reading": [
        { "01":"<span class='lem'>daz</span> ] <span class='rdg'>÷az <a>O</a></span>" },
        { "02":"<span class='lem'>senftert</span> ] <span class='rdg'>Senfter <a>U</a> <a>Q</a> Senffte <a>W</a> (<a>O</a> <a>Fr40</a>) Senffrette <a>R</a></span>" },
        { "03":"<span class='lem'>müese</span> ] <span class='rdg'>muͦze <a>U</a> (<a>O</a>) must <a>Q</a> im <a>R</a></span>" },
        { "03":"<span class='lem'>im</span> ] <span class='rdg'>nu <a>Q</a> mu̽ste <a>R</a></span>" },
        { "04":"<span class='lem'>swaz</span> ] <span class='rdg'>Waz <a>U</a> (<a>W</a> <a>R</a>) Wo <a>Q</a></span>" },
        { "04":"<span class='lem'>dâ</span> ] <span class='rdg'>do <a>U</a> <a>V</a> <a>W</a></span>" },
        { "04":"<span class='lem'>was</span> ] <span class='rdg'>wer <a>R</a></span>" },
        { "05":"<span class='lem'>ir clâren</span> ] <span class='rdg'>irē clarem <a>Q</a> ieren claren <a>R</a> ir klarem <a>Fr40</a></span>" },
        { "07":"<span class='lem'>kom</span> ] <span class='rdg'>keme <a>R</a></span>" },
        { "08":"<span class='lem'>si</span> ] <span class='rdg'><span class='note'>om.</span> <a>U</a> sy im <a>W</a> <a>R</a> (<a>O</a>)</span>" },
        { "08":"<span class='lem'>im</span> ] <span class='rdg'>[*]: im ir <a>V</a> ym ir <a>Q</a> (<a>Fr40</a>) ir <a>W</a> <a>O</a> <a>R</a></span>" },
        { "10":"<span class='lem'>iuch</span> ] <span class='rdg'>iv <a>T</a></span>" },
        { "10":"<span class='lem'>kumber</span> ] <span class='rdg'>zorne <a>U</a> <a>V</a> <a>W</a> (<a>O</a>) <a>Q</a> <a>R</a> <a>Fr40</a></span>" },
        { "12":"<span class='lem'>im</span> ] <span class='rdg'><span class='note'>om.</span> <a>O</a></span>" },
        { "13":"<span class='lem'>ers</span> ] <span class='rdg'>er des <a>O</a></span>" },
        { "14":"<span class='lem'>daz</span> ] <span class='rdg'>Vnde <a>V</a></span>" },
        { "14":"<span class='lem'>lasters</span> ] <span class='rdg'>laster <a>Q</a></span>" },
        { "14":"<span class='lem'>æhte</span> ] <span class='rdg'>ehe <a>T</a></span>" },
        { "15":"<span class='lem'>einem site</span> ] <span class='rdg'>gvͦtem willen <a>O</a> einen sitten <a>R</a></span>" },
        { "17":"<span class='lem'>sîn</span> ] <span class='rdg'>si <a>T</a></span>" },
        { "17":"<span class='lem'>die</span> ] <span class='rdg'>div <a>T</a> <a>O</a></span>" },
        { "18":"<span class='lem'>ich</span> ] <span class='rdg'>och <a>R</a></span>" },
        { "19":"<span class='lem'>wande</span> ] <span class='rdg'>Wan si <a>O</a></span>" },
        { "19":"<span class='lem'>der künec</span> ] <span class='rdg'><span class='note'>om.</span> <a>O</a></span>" },
        { "19":"<span class='lem'>kinde</span> ] <span class='rdg'>sippe <a>Q</a></span>" },
        { "20":"<span class='lem'>im</span> ] <span class='rdg'>ir <a>U</a> <a>V</a> <a>W</a> <a>O</a> (<a>R</a>) <a>Fr40</a></span>" },
        { "21":"<span class='lem'>hülfe</span> ] <span class='rdg'>huffe <a>R</a></span>" },
        { "22":"<span class='lem'>juncvrowen</span> ] <span class='rdg'>ivncvrowe <a>T</a></span>" },
        { "22":"<span class='lem'>sunder</span> ] <span class='rdg'>bisvnder <a>V</a> (<a>O</a>)</span>" },
        { "22":"<span class='lem'>sprach</span> ] <span class='rdg'>gesprach <a>V</a> besprach <a>Q</a></span>" },
        { "23":"<span class='lem'>dô</span> ] <span class='rdg'>Die <a>W</a></span>" },
        { "23":"<span class='lem'>er</span> ] <span class='rdg'>der <a>Q</a></span>" },
        { "24":"<span class='lem'>muose</span> ] <span class='rdg'>mvese <a>T</a></span>" },
        { "24":"<span class='lem'>hôhen</span> ] <span class='rdg'><span class='note'>om.</span> <a>Q</a></span>" },
        { "25":"<span class='lem'>sus</span> ] <span class='rdg'>Als <a>Q</a></span>" },
        { "26":"<span class='lem'>solch</span> ] <span class='rdg'>swelch <a>T</a></span>" },
        { "26":"<span class='lem'>im</span> ] <span class='rdg'><span class='note'>om.</span> <a>Fr40</a></span>" },
        { "27":"<span class='lem'>vorlouf</span> ] <span class='rdg'>wint <a>V</a></span>" },
        { "27":"<span class='lem'>leitehunt</span> ] <span class='rdg'>vorleydehúnt <a>Q</a></span>" },
        { "28":"<span class='lem'>als ein hunt</span> ] <span class='rdg'>[*]: as sin mvnt <a>V</a> az sin mvnt <a>O</a> (<a>Q</a> <a>R</a> <a>Fr40</a>)</span>" },
        { "29":"<span class='rdg'>[*]: Mit in do vier wochen <a>V</a></span>" },
        { "29":"<span class='lem'>az er</span> ] <span class='rdg'><span class='note'>om.</span> <a>W</a> <a>O</a> <a>Q</a> <a>R</a> <a>Fr40</a></span>" },
        { "29":"<span class='lem'>in</span> ] <span class='rdg'>im <a>U</a> In do <a>R</a> in do essen <a>W</a> in da <a>O</a> <a>Fr40</a> im do <a>Q</a></span>" },
        { "30":"<span class='lem'>sus</span> ] <span class='rdg'>Als <a>Q</a></span>" }
      ],
      "handle": "*T",
      "distribution": "<ul><li><a data-thirties=\"528\">T</a></li><li><a data-thirties=\"528\">U</a></li><li><a data-thirties=\"528\">V</a></li><li><a data-thirties=\"528\">W</a></li><li><a data-thirties=\"528\">O</a></li><li><a data-thirties=\"528\">Q</a></li><li><a data-thirties=\"528\">R</a></li><li><a data-thirties=\"528\">Fr40</a></li></ul>",
      "structure": [
        { "01":"<span class='note'>Initiale</span> <a>W</a> <a>O</a> <a>Fr40</a>" },
        { "11":"<span class='note'>Majuskel</span> <a>T</a>" }
      ]
    }
  ],
  "meta": {
    "generated-by": "parzival-static-api/src/generate.xsl",
    "task": "metadata-syn-apps",
    "generated-on": "2026-02-02T20:32:21.639161207+01:00",
    "description": "Apparatus information (distribution, structural, readings)."
  }
}