{
  "versions": [
    {
      "reading": [ { "28":"<span class='lem'>Munsalvæsche</span> ] <span class='rdg'>Mvnsalvæsce <a>D</a></span>" } ],
      "handle": "*D",
      "distribution": "<ul><li>D</li></ul>",
      "structure": [
        { "01":"<span class='note'>Initiale</span> <a>D</a>" },
        { "09":"<span class='note'>Majuskel</span> <a>D</a>" },
        { "19":"<span class='note'>Majuskel</span> <a>D</a>" },
        { "27":"<span class='note'>Majuskel</span> <a>D</a>" }
      ]
    },
    {
      "reading": [
        { "01":"<span class='rdg'>Er beginc wunders so vil <a>V'</a></span>" },
        { "02":"<span class='rdg'>Daz ich nit alles sagen wil <span class='note'>(Fortsetzung in 824.23)</span> <a>V'</a></span>" },
        { "03":"<span class='rdg'><span class='note'>Die Verse 824.3-22 fehlen</span> <a>V'</a></span>" },
        { "04":"<span class='rdg'><span class='note'>Die Verse 824.4-7 fehlen</span> <a>W</a></span>" },
        { "04":"<span class='lem'>hôchvart</span> ] <span class='rdg'>hoher art <a>V</a></span>" },
        { "06":"<span class='lem'>gebâren</span> ] <span class='rdg'>bewarn <a>m</a></span>" },
        { "07":"<span class='lem'>warp</span> ] <span class='rdg'>erstarp <a>m</a> [*]: erwarb <a>V</a></span>" },
        { "08":"<span class='lem'>gir</span> ] <span class='rdg'>begir <a>n</a></span>" },
        { "17":"<span class='lem'>einen</span> ] <span class='rdg'>ein <a>m</a> <a>n</a> <a>V</a></span>" },
        { "18":"<span class='lem'>in</span> ] <span class='rdg'>ir <a>W</a></span>" },
        { "19":"<span class='lem'>verlân</span> ] <span class='rdg'>gelan <a>n</a> erlan <a>W</a></span>" },
        { "20":"<span class='lem'>waz</span> ] <span class='rdg'>Swaz <a>V</a></span>" },
        { "21":"<span class='lem'>si</span> ] <span class='rdg'>sich <a>m</a> <a>n</a></span>" },
        { "22":"<span class='lem'>einen</span> ] <span class='rdg'>Ein <a>V</a></span>" },
        { "22":"<span class='lem'>ir landes hêrren</span> ] <span class='rdg'>ir vor den herren <a>m</a> <a>n</a> vor den herren <a>W</a></span>" },
        { "23":"<span class='rdg'><span class='note'>statt 824.23-826.2:</span> Wie er zu der herzoginnen gein brabant quam <span class='note'>(vgl. 825.15:</span> herzogîn<span class='note'>)</span> / Vnd die zu einer amyen nam <span class='note'>(Fortsetzung von 824.2; weiterer Text in 826.23)</span> <a>V'</a></span>" },
        { "23":"<span class='lem'>verrem</span> ] <span class='rdg'>femrem <a>m</a></span>" },
        { "24":"<span class='lem'>hin</span> ] <span class='rdg'><span class='note'>om.</span> <a>W</a></span>" },
        { "24":"<span class='lem'>die man si</span> ] <span class='rdg'>do man su̽ <a>m</a> (<a>n</a>) do sy manne <a>W</a></span>" },
        { "27":"<span class='lem'>vürstîn</span> ] <span class='rdg'>fúrsten <a>n</a></span>" },
        { "27":"<span class='lem'>Brabant</span> ] <span class='rdg'>brobant <a>n</a> probrant <a>V</a> probant <a>W</a></span>" },
        { "28":"<span class='lem'>Muntsalvasche</span> ] <span class='rdg'>muntsaluasce <a>m</a> <a>n</a> munsalfasce <a>V</a> montsaluatsch <a>W</a> </span>" },
        { "29":"<span class='lem'>den der</span> ] <span class='rdg'>den het der <a>m</a></span>" }
      ],
      "handle": "*m",
      "distribution": "<ul><li>m</li><li>n</li><li>V</li><li>V'</li><li>W</li></ul>",
      "structure": [ { "01":"<span class='note'>Initiale</span> <a>V</a> <a>W</a>" } ]
    },
    {
      "reading": [
        { "03":"<span class='lem'>vor</span> ] <span class='rdg'>von <a>G</a></span>" },
        { "04":"<span class='lem'>hôher</span> ] <span class='rdg'>solher <a>Z</a></span>" },
        { "05":"<span class='lem'>bêde</span> ] <span class='rdg'>beidiu <a>I</a></span>" },
        { "05":"<span class='lem'>wâren</span> ] <span class='rdg'>[wart]: waren <a>Z</a></span>" },
        { "07":"<span class='lem'>erwarp</span> ] <span class='rdg'>warp <a>Z</a></span>" },
        { "08":"<span class='lem'>al</span> ] <span class='rdg'>Daz <a>L</a></span>" },
        { "15":"<span class='lem'>si</span> ] <span class='rdg'>si alle <a>I</a> an sie <a>Z</a></span>" },
        { "16":"<span class='lem'>sich</span> ] <span class='rdg'><span class='note'>om.</span> <a>L</a></span>" },
        { "19":"<span class='lem'>gar</span> ] <span class='rdg'><span class='note'>om.</span> <a>I</a></span>" },
        { "20":"<span class='lem'>swaz</span> ] <span class='rdg'>Waz <a>L</a> <a>Z</a></span>" },
        { "21":"<span class='lem'>unschulde</span> ] <span class='rdg'>vnshuldic <a>I</a></span>" },
        { "22":"<span class='lem'>sir</span> ] <span class='rdg'>vor ir <a>I</a> sý zu̽ ir <a>L</a></span>" },
        { "22":"<span class='lem'>landes hêrren</span> ] <span class='rdg'>lantherren <a>L</a></span>" },
        { "22":"<span class='lem'>sprach</span> ] <span class='rdg'>si sprach <a>I</a></span>" },
        { "23":"<span class='lem'>verren landen</span> ] <span class='rdg'>verrem lande <a>I</a></span>" },
        { "24":"<span class='lem'>hin</span> ] <span class='rdg'>hinz <a>I</a></span>" },
        { "25":"<span class='lem'>des si</span> ] <span class='rdg'>si des <a>G</a></span>" },
        { "25":"<span class='lem'>bewîste</span> ] <span class='rdg'>[bewiste]: beweiste <a>Z</a></span>" },
        { "26":"<span class='lem'>brîste</span> ] <span class='rdg'>leiste <a>Z</a></span>" },
        { "28":"<span class='lem'>Muntsalvatsche</span> ] <span class='rdg'>muntshaluasche <a>I</a> montsalvatsche <a>Z</a></span>" },
        { "28":"<span class='lem'>gesant</span> ] <span class='rdg'>ir gesant <a>Z</a></span>" },
        { "29":"<span class='lem'>der den</span> ] <span class='rdg'>Den <a>Z</a></span>" },
        { "29":"<span class='lem'>swane</span> ] <span class='rdg'>shonen <a>I</a></span>" }
      ],
      "handle": "*G",
      "distribution": "<ul><li>G</li><li>I</li><li>L</li><li>Z</li></ul>",
      "structure": [
        { "01":"<span class='note'>Initiale</span> <a>G</a> <a>I</a> <a>L</a> <a>Z</a>" },
        { "19":"<span class='note'>Initiale</span> <a>I</a>" }
      ]
    },
    {
      "reading": [
        { "01":"<span class='rdg'><span class='note'>Die Verse 821.21-826.30 fehlen</span> <a>Q</a></span>" },
        { "02":"<span class='lem'>über</span> ] <span class='rdg'>úwer <a>R</a></span>" },
        { "04":"<span class='lem'>hôhiu</span> ] <span class='rdg'>hocher <a>R</a></span>" },
        { "07":"<span class='lem'>warp</span> ] <span class='rdg'>erwarb <a>R</a></span>" },
        { "08":"<span class='rdg'>All weltlich [dins]: ding an Jr erwarb <a>R</a></span>" },
        { "14":"<span class='lem'>ir</span> ] <span class='rdg'>irn <a>U</a></span>" },
        { "16":"<span class='lem'>wolte</span> ] <span class='rdg'>wolten <a>U</a></span>" },
        { "19":"<span class='lem'>gar</span> ] <span class='rdg'>gancz <a>R</a></span>" },
        { "21":"<span class='lem'>sprach</span> ] <span class='rdg'>zoch <a>R</a></span>" },
        { "23":"<span class='lem'>verrem lande</span> ] <span class='rdg'>ferren landen <a>R</a></span>" },
        { "24":"<span class='lem'>si</span> ] <span class='rdg'>so <a>R</a></span>" },
        { "26":"<span class='lem'>si</span> ] <span class='rdg'><span class='note'>om.</span> <a>R</a></span>" },
        { "27":"<span class='lem'>vürstinne</span> ] <span class='rdg'>ein stime <a>R</a></span>" },
        { "27":"<span class='lem'>Brabant</span> ] <span class='rdg'>farbant <a>R</a></span>" },
        { "28":"<span class='lem'>Munsalvasche</span> ] <span class='rdg'>Muntsalvatsche <a>U</a> Munsaualesche <a>R</a></span>" },
        { "29":"<span class='lem'>der</span> ] <span class='rdg'>Dar <a>U</a> Die der <a>R</a></span>" },
        { "29":"<span class='lem'>brâhte</span> ] <span class='rdg'>brechte <a>R</a></span>" },
        { "30":"<span class='lem'>gedâhte</span> ] <span class='rdg'>gedechtte <a>R</a></span>" }
      ],
      "handle": "*T",
      "distribution": "<ul><li>U</li><li>Q</li><li>R</li></ul>",
      "structure": [
        { "01":"<span class='note'>Initiale</span> <a>R</a>" },
        { "22":"<span class='note'>Initiale</span> <a>R</a>" }
      ]
    }
  ],
  "meta": {
    "generated-by": "parzival-static-api/src/generate.xsl",
    "task": "metadata-syn-apps",
    "generated-on": "2025-05-29T00:08:29.556314971+02:00",
    "description": "Apparatus information (distribution, structural, readings)."
  }
}