{
  "versions": [
    {
      "reading": [
        { "05":"<span class='lem'>rîterschaft</span> ] <span class='rdg'>reterschaft <a>D</a></span>" },
        { "11":"<span class='lem'>er</span> ] <span class='rdg'><span class='note'>om.</span> <a>D</a></span>" },
        { "17":"<span class='lem'>Anschouwe</span> ] <span class='rdg'>Anscoͮwe <a>D</a></span>" },
        { "23":"<span class='lem'>Kaylete</span> ] <span class='rdg'>kaylette <a>D</a></span>" },
        { "24":"<span class='lem'>Schoette</span> ] <span class='rdg'>Scoette <a>D</a></span>" }
      ],
      "handle": "*D",
      "distribution": "<ul><li><a>D</a></li></ul>",
      "structure": [
        { "09":"<span class='note'>Initiale</span> <a>D</a>" },
        { "23":"<span class='note'>Majuskel</span> <a>D</a>" }
      ]
    },
    {
      "reading": [
        { "03":"<span class='rdg'>Der zedel erdeden gekeren <a>o</a></span>" },
        { "04":"<span class='lem'>trûren</span> ] <span class='rdg'>trúten <a>o</a></span>" },
        { "07":"<span class='lem'>Galoes</span> ] <span class='rdg'>galeus <a>m</a> goloes <a>o</a></span>" },
        { "07":"<span class='lem'>mîner</span> ] <span class='rdg'>minne <a>m</a></span>" },
        { "09":"<span class='lem'>er</span> ] <span class='rdg'><span class='note'>om.</span> <a>n</a></span>" },
        { "10":"<span class='lem'>sîn</span> ] <span class='rdg'>sin sin <a>n</a></span>" },
        { "13":"<span class='lem'>landes</span> ] <span class='rdg'>lande <a>n</a> [lande]: landes <a>o</a></span>" },
        { "17":"<span class='lem'>Anschouwe</span> ] <span class='rdg'>aschowe <a>o</a></span>" },
        { "19":"<span class='lem'>enwart</span> ] <span class='rdg'>wart <a>n</a> <a>o</a></span>" },
        { "20":"<span class='lem'>minne</span> ] <span class='rdg'>woren mẏnne <a>n</a> woren mynnen <a>o</a></span>" },
        { "21":"<span class='lem'>dînem</span> ] <span class='rdg'>deme <a>o</a></span>" },
        { "23":"<span class='lem'>Kailete</span> ] <span class='rdg'>kailette <a>m</a> kailet <a>n</a> <a>o</a></span>" },
        { "24":"<span class='lem'>Schoiete</span> ] <span class='rdg'>schoẏet <a>n</a> schaiete <a>o</a></span>" },
        { "28":"<span class='lem'>Galoes</span> ] <span class='rdg'>galaes <a>o</a></span>" },
        { "29":"<span class='lem'>sach</span> ] <span class='rdg'>gesach <a>n</a></span>" },
        { "30":"<span class='lem'>tôt</span> ] <span class='rdg'>tet <a>m</a></span>" }
      ],
      "handle": "*m",
      "distribution": "<ul><li><a>m</a></li><li><a>n</a></li><li><a>o</a></li></ul>",
      "structure": [ { "10":"<span class='note'>Initiale</span> <a>m</a>" } ]
    },
    {
      "reading": [
        { "01":"<span class='lem'>si</span> ] <span class='rdg'>÷i <a>O</a></span>" },
        { "01":"<span class='lem'>breite</span> ] <span class='rdg'>brete <a>R</a></span>" },
        { "02":"<span class='lem'>jâmers</span> ] <span class='rdg'>iamer <a>Q</a></span>" },
        { "03":"<span class='lem'>zer</span> ] <span class='rdg'>Zu <a>Q</a></span>" },
        { "03":"<span class='lem'>erden</span> ] <span class='rdg'>erde <a>O</a> <a>L</a> <a>Q</a> <a>R</a> <a>Fr21</a> [erde*]: erde <a>Z</a></span>" },
        { "03":"<span class='lem'>gekêret</span> ] <span class='rdg'>gecherte <a>O</a> koret <a>R</a></span>" },
        { "04":"<span class='lem'>trûren</span> ] <span class='rdg'>iamer <a>G</a> truten <a>M</a> trúwe <a>R</a></span>" },
        { "04":"<span class='lem'>daz</span> ] <span class='rdg'><span class='note'>om.</span> <a>I</a></span>" },
        { "04":"<span class='lem'>lêret</span> ] <span class='rdg'>lerte <a>O</a> lerent <a>Q</a></span>" },
        { "05":"<span class='lem'>alsô</span> ] <span class='rdg'>Asvs <a>O</a> Alsus <a>L</a> <a>M</a> <a>Q</a> <a>R</a> <a>Z</a> (<a>Fr21</a>)</span>" },
        { "05":"<span class='lem'>tuont</span> ] <span class='rdg'>tut <a>Q</a></span>" },
        { "06":"<span class='lem'>unt</span> ] <span class='rdg'>Sie <a>Z</a></span>" },
        { "06":"<span class='lem'>verladen</span> ] <span class='rdg'>úberladen <a>R</a></span>" },
        { "07":"<span class='lem'>sît</span> ] <span class='rdg'>Mit <a>Q</a></span>" },
        { "07":"<span class='lem'>Galoes</span> ] <span class='rdg'>Gaoles <a>L</a></span>" },
        { "07":"<span class='rdg'><span class='note'>nach 92.7:</span> Das er nicht lenger solt vertún <a>Q</a></span>" },
        { "08":"<span class='rdg'>nach minne dienst (Nach mynne <a>L</a> Nach minnen <a>Z</a> Nach minnen [reht] <a>Fr21</a>) niht solte (sol dinst <a>L</a> dinst sol <a>Fr21</a>) tuͤn <a>I</a> (<a>O</a> <a>L</a> <a>M</a> <a>R</a> <a>Z</a> <a>Fr21</a>) · Nach minne dinst seiner tage <a>Q</a></span>" },
        { "08":"<span class='rdg'><span class='note'>nach 92.8:</span> Das was auch ir aller clage <a>Q</a></span>" },
        { "09":"<span class='lem'>dô</span> ] <span class='rdg'>Da <a>Z</a> ÷O <a>Fr21</a></span>" },
        { "09":"<span class='lem'>er gevriesch</span> ] <span class='rdg'>vornam <a>M</a> er clagt <a>R</a> grefriesch <a>Fr21</a></span>" },
        { "09":"<span class='lem'>des</span> ] <span class='rdg'>sins <a>R</a></span>" },
        { "10":"<span class='lem'>was sîn</span> ] <span class='rdg'>die <a>Z</a></span>" },
        { "10":"<span class='lem'>herzenôt</span> ] <span class='rdg'>not <a>I</a> [not]: hertzen not <a>Z</a></span>" },
        { "11":"<span class='lem'>er</span> ] <span class='rdg'><span class='note'>om.</span> <a>I</a></span>" },
        { "12":"<span class='lem'>sus</span> ] <span class='rdg'>vnsz <a>Q</a> nu <a>Z</a></span>" },
        { "12":"<span class='lem'>ort</span> ] <span class='rdg'>not <a>M</a></span>" },
        { "13":"<span class='lem'>riwe</span> ] <span class='rdg'>trewe <a>Q</a></span>" },
        { "13":"<span class='lem'>landes</span> ] <span class='rdg'>lendes <a>I</a></span>" },
        { "14":"<span class='lem'>teter</span> ] <span class='rdg'>der e tet er <a>Q</a></span>" },
        { "14":"<span class='lem'>dô</span> ] <span class='rdg'>da <a>M</a> doch <a>Z</a></span>" },
        { "15":"<span class='lem'>Grôz</span> ] <span class='rdg'>Sein <a>Q</a> (<a>R</a>)</span>" },
        { "15":"<span class='lem'>riwe</span> ] <span class='rdg'>trew <a>Q</a></span>" },
        { "15":"<span class='lem'>im hertes</span> ] <span class='rdg'>im grozes <a>O</a> (<a>L</a>) <a>Fr21</a> syme herczin <a>M</a> im <a>Z</a> im grossers <a>Q</a></span>" },
        { "15":"<span class='lem'>kumbers</span> ] <span class='rdg'>kvmber <a>Fr21</a></span>" },
        { "16":"<span class='lem'>hêrre</span> ] <span class='rdg'>helt <a>O</a> <a>L</a> <a>M</a> <a>Q</a> (<a>R</a>) <a>Z</a> <a>Fr21</a></span>" },
        { "16":"<span class='lem'>grôzen</span> ] <span class='rdg'>waren <a>O</a> (<a>L</a> <a>M</a> <a>Q</a> <a>R</a>) [ian]: waren <a>Z</a></span>" },
        { "16":"<span class='lem'>triwen</span> ] <span class='rdg'>riwen <a>O</a></span>" },
        { "17":"<span class='lem'>Anschouwe</span> ] <span class='rdg'>anschoͮwe <a>G</a> antschoͮe <a>I</a> anschawe <a>O</a> Anschowe <a>L</a> (<a>Q</a> <a>R</a>) anscowe <a>M</a> antschowe <a>Z</a> :::schoͮwe <a>Fr21</a></span>" },
        { "17":"<span class='lem'>Galoes</span> ] <span class='rdg'>der Galoes <a>O</a> Gaoles <a>L</a></span>" },
        { "18":"<span class='lem'>darf</span> ] <span class='rdg'>endarf <a>I</a> durff <a>M</a> tar <a>R</a></span>" },
        { "19":"<span class='lem'>enwart</span> ] <span class='rdg'>wart <a>Q</a></span>" },
        { "19":"<span class='lem'>nie</span> ] <span class='rdg'><span class='note'>om.</span> <a>Z</a></span>" },
        { "19":"<span class='lem'>manlîcher</span> ] <span class='rdg'>mynneclicher <a>L</a></span>" },
        { "20":"<span class='lem'>der</span> ] <span class='rdg'><span class='note'>om.</span> <a>I</a> de <a>O</a></span>" },
        { "20":"<span class='lem'>rehten milte</span> ] <span class='rdg'>rehter milte <a>I</a> warn milte <a>O</a> (<a>L</a> <a>Q</a> <a>R</a> <a>Z</a> <a>Fr21</a>) milde warin <a>M</a></span>" },
        { "21":"<span class='lem'>dînem</span> ] <span class='rdg'>einem <a>O</a> sinem <a>Z</a></span>" },
        { "21":"<span class='lem'>herzen</span> ] <span class='rdg'>hertze <a>Q</a></span>" },
        { "22":"<span class='lem'>erbarmet</span> ] <span class='rdg'>erbarmde <a>O</a></span>" },
        { "22":"<span class='lem'>mich dîn</span> ] <span class='rdg'>dich min <a>Z</a> mich dev <a>Fr21</a></span>" },
        { "23":"<span class='rdg'><span class='note'>Versfolge 92.24-23</span> <a>O</a></span>" },
        { "23":"<span class='lem'>Kailet</span> ] <span class='rdg'>Gahilete <a>I</a> kaylet <a>O</a> <a>L</a> <a>Q</a> <a>R</a> (<a>Fr21</a>) Gailet <a>Z</a></span>" },
        { "24":"<span class='lem'>gehabet</span> ] <span class='rdg'>gehap <a>L</a></span>" },
        { "24":"<span class='lem'>Tuschet</span> ] <span class='rdg'>ieskutte <a>I</a> tschvet <a>O</a> Joet <a>L</a> tscowet <a>M</a> ahoet <a>Q</a> Schoet <a>R</a> thschvet <a>Z</a> Tsvet <a>Fr21</a></span>" },
        { "26":"<span class='lem'>sô</span> ] <span class='rdg'><span class='note'>om.</span> <a>I</a> <a>L</a></span>" },
        { "27":"<span class='lem'>dô</span> ] <span class='rdg'>daz <a>I</a> Da <a>M</a> <a>Z</a></span>" },
        { "27":"<span class='lem'>ir</span> ] <span class='rdg'><span class='note'>om.</span> <a>M</a> <a>R</a> <a>Fr21</a></span>" },
        { "27":"<span class='lem'>Gandin</span> ] <span class='rdg'>candin <a>I</a> gaudin <a>Q</a></span>" },
        { "28":"<span class='lem'>Galoes</span> ] <span class='rdg'>Gaoles <a>L</a> Goloes <a>R</a></span>" },
        { "28":"<span class='lem'>dîn</span> ] <span class='rdg'>min <a>I</a> [min din]: din <a>R</a></span>" },
        { "29":"<span class='lem'>si dîn</span> ] <span class='rdg'>sit ich <a>I</a> do si dich <a>O</a> (<a>Q</a> <a>R</a>) <a>Fr21</a> do sie din <a>L</a> da sie dyn <a>M</a> (<a>Z</a>)</span>" },
        { "29":"<span class='lem'>bî ir niht</span> ] <span class='rdg'>nit by ir <a>R</a></span>" },
        { "29":"<span class='lem'>sach</span> ] <span class='rdg'>enshach <a>I</a></span>" },
        { "30":"<span class='lem'>ir ouch</span> ] <span class='rdg'>avch <a>O</a> (<a>L</a> <a>M</a> <a>Q</a> <a>R</a> <a>Z</a> <a>Fr21</a>)</span>" },
        { "30":"<span class='lem'>ir herze</span> ] <span class='rdg'>herze <a>I</a> (<a>M</a>)</span>" }
      ],
      "handle": "*G",
      "distribution": "<ul><li><a>G</a></li><li><a>I</a></li><li><a>O</a></li><li><a>L</a></li><li><a>M</a></li><li><a>Q</a></li><li><a>R</a></li><li><a>Z</a></li><li><a>Fr21</a></li></ul>",
      "structure": [
        { "01":"<span class='note'>Initiale</span> <a>O</a>" },
        { "09":"<span class='note'>Initiale</span> <a>I</a> <a>L</a> <a>R</a> <a>Z</a> <a>Fr21</a>" },
        { "15":"<span class='note'>Initiale</span> <a>G</a>" },
        { "15":"<span class='note'>Capitulumzeichen</span> <a>L</a>" }
      ]
    },
    {
      "reading": [
        { "01":"<span class='lem'>si hânt</span> ] <span class='rdg'>[*]: An <a>V</a></span>" },
        { "01":"<span class='lem'>schiltes</span> ] <span class='rdg'>scilte <a>T</a></span>" },
        { "01":"<span class='lem'>breite</span> ] <span class='rdg'>gebraite <a>W</a></span>" },
        { "03":"<span class='lem'>gein der erden</span> ] <span class='rdg'>Gegen der erde <a>W</a> zerde <a>T</a></span>" },
        { "04":"<span class='lem'>trûren</span> ] <span class='rdg'>truwe <a>V</a> (<a>T</a>)</span>" },
        { "04":"<span class='lem'>si</span> ] <span class='rdg'>si doch <a>T</a></span>" },
        { "04":"<span class='lem'>lêret</span> ] <span class='rdg'><span class='note'>om.</span> <a>U</a> lerte <a>T</a></span>" },
        { "06":"<span class='lem'>beladen</span> ] <span class='rdg'>úberladen <a>W</a> verladen <a>T</a></span>" },
        { "06":"<span class='lem'>jâmers</span> ] <span class='rdg'>leides <a>T</a></span>" },
        { "07":"<span class='lem'>Galoes</span> ] <span class='rdg'>Gales <a>U</a></span>" },
        { "08":"<span class='rdg'>Nach meinem dienst nit sol thun <a>W</a> · nach dienste niht solte minne tvͦn <a>T</a></span>" },
        { "08":"<span class='lem'>minnen</span> ] <span class='rdg'>minne <a>V</a></span>" },
        { "08":"<span class='lem'>solte</span> ] <span class='rdg'><span class='note'>om.</span> <a>U</a></span>" },
        { "09":"<span class='lem'>ervriesch</span> ] <span class='rdg'>erfuͦr <a>V</a> <a>W</a> vriesc <a>T</a></span>" },
        { "10":"<span class='lem'>herzenôt</span> ] <span class='rdg'>hertzen not <a>W</a></span>" },
        { "13":"<span class='lem'>riuwe</span> ] <span class='rdg'>ruwen <a>V</a> (<a>W</a>)</span>" },
        { "13":"<span class='lem'>leides</span> ] <span class='rdg'>in leides <a>V</a> landes <a>W</a> <a>T</a></span>" },
        { "14":"<span class='lem'>diu</span> ] <span class='rdg'>der <a>V</a> (<a>W</a>) <a>T</a></span>" },
        { "14":"<span class='lem'>sich dô</span> ] <span class='rdg'>doch sich <a>V</a></span>" },
        { "15":"<span class='lem'>im hertes kumbers</span> ] <span class='rdg'>im hertez kuͦmers <a>U</a> sin hertze kumbers <a>V</a> in seinem hertzen kummer <a>W</a> im kvmbers <a>T</a></span>" },
        { "16":"<span class='lem'>ûz</span> ] <span class='rdg'>mit <a>T</a></span>" },
        { "17":"<span class='lem'>Anschouwe</span> ] <span class='rdg'>Anscheuwe <a>U</a> Anschowe <a>V</a> antschowe <a>W</a></span>" },
        { "17":"<span class='lem'>Galoes</span> ] <span class='rdg'>Gales <a>U</a></span>" },
        { "19":"<span class='lem'>enwart nie</span> ] <span class='rdg'>ward mit <a>W</a></span>" },
        { "20":"<span class='lem'>minnen</span> ] <span class='rdg'>[mil*]: milte <a>V</a> minne <a>W</a> <a>T</a></span>" },
        { "23":"<span class='lem'>zuo</span> ] <span class='rdg'>sa ze <a>T</a></span>" },
        { "23":"<span class='lem'>Kaylete</span> ] <span class='rdg'>kalete <a>U</a> kaẏlete <a>V</a> gaylete <a>W</a> kaylet <a>T</a></span>" },
        { "24":"<span class='lem'>Tscheuwete</span> ] <span class='rdg'>Tschewete <a>U</a> Schewete <a>V</a> deschawete <a>W</a> Tscêuwet <a>T</a></span>" },
        { "25":"<span class='lem'>vreuden</span> ] <span class='rdg'>an froͤden <a>V</a></span>" },
        { "26":"<span class='lem'>sich</span> ] <span class='rdg'>[*]: es <a>V</a></span>" },
        { "27":"<span class='lem'>ir erstarp</span> ] <span class='rdg'>er erstarp <a>U</a> erstarp <a>V</a> ir starb <a>W</a> (<a>T</a>)</span>" },
        { "27":"<span class='lem'>Gandin</span> ] <span class='rdg'>Gaudin <a>U</a> (<a>W</a>)</span>" },
        { "28":"<span class='lem'>Galoes</span> ] <span class='rdg'>Gales <a>U</a></span>" },
        { "28":"<span class='lem'>dîn</span> ] <span class='rdg'>[*]: din <a>V</a> min <a>W</a> <a>T</a></span>" },
        { "29":"<span class='rdg'><span class='note'>Versfolge 92.30-29</span> <a>U</a></span>" },
        { "29":"<span class='lem'>den bî ir niht</span> ] <span class='rdg'>[*]: dich niht bi ir <a>V</a> den nit bei ir <a>W</a> (<a>T</a>)</span>" },
        { "29":"<span class='lem'>sach</span> ] <span class='rdg'>vand <a>W</a></span>" },
        { "30":"<span class='rdg'>Von dem ir freúde gar verschwand <a>W</a></span>" },
        { "30":"<span class='lem'>daz</span> ] <span class='rdg'>ir <a>T</a></span>" }
      ],
      "handle": "*T",
      "distribution": "<ul><li><a>U</a></li><li><a>V</a></li><li><a>W</a></li><li><a>T</a></li></ul>",
      "structure": [
        { "09":"<span class='note'>Initiale</span> <a>V</a> <a>W</a> <a>T</a>" },
        { "23":"<span class='note'>Majuskel</span> <a>T</a>" },
        { "30":"<span class='note'>Majuskel</span> <a>T</a>" }
      ]
    }
  ],
  "meta": {
    "generated-by": "parzival-static-api/src/generate.xsl",
    "task": "metadata-syn-apps",
    "generated-on": "2025-07-01T10:03:49.067118886+02:00",
    "description": "Apparatus information (distribution, structural, readings)."
  }
}